{
  "animeTitle": "Natsume Yuujinchou Shichi",
  "type": "Fall 2024 Anime",
  "releasedDate": "2024",
  "status": "Ongoing",
  "genres": [
    "Iyashikei",
    "Mythology",
    "Shoujo",
    "Slice of Life",
    "Supernatural"
  ],
  "otherNames": "Natsume's Book of Friends Season 7, \u590f\u76ee\u53cb\u4eba\u5e33 \u6f06",
  "synopsis": "Seventh season of Natsume Yuujinchou.",
  "animeImg": "https://gogocdn.net/cover/natsume-yuujinchou-shichi.png",
  "totalEpisodes": "4",
  "episodesList": [
    {
      "episodeId": "natsume-yuujinchou-shichi-episode-4",
      "episodeNum": "Episode 4"
    },
    {
      "episodeId": "natsume-yuujinchou-shichi-episode-3",
      "episodeNum": "Episode 3"
    },
    {
      "episodeId": "natsume-yuujinchou-shichi-episode-2",
      "episodeNum": "Episode 2"
    },
    {
      "episodeId": "natsume-yuujinchou-shichi-episode-1",
      "episodeNum": "Episode 1"
    }
  ]
}