{
  "animeTitle": "Strange Dawn (Dub)",
  "type": "TV Series",
  "releasedDate": "2000",
  "status": "Completed",
  "genres": [
    "Adventure",
    "Drama",
    "Fantasy"
  ],
  "otherNames": "\u30b9\u30c8\u30ec\u30f3\u30b8\u30fb\u30c9\u30fc\u30f3",
  "synopsis": "Yuko and Eri are two normal girls who are sucked into the alternate world filled with tiny people. The people of this mysterious world sees them as their \"Great Protectors\" who can protect their land in a time of strife. The two girls set out on a mission with a group of warriors from the village to find out how they were brought here and how might they return home. However, there is a war brewing and these two Great Protectors are the political tool that every faction lusts for to rally the people to their side.",
  "animeImg": "https://gogocdn.net/cover/strange-dawn-dub.png",
  "totalEpisodes": "7"
}