{
  "title": "Yuri On Livestream, Yaoi Behind The Screen",
  "img": "https://avt.mkklcdnv6temp.com/fld/40/a/18-1733329612-nw.webp",
  "alternative_title": "Usotsuki Yuri Haishin, Buchikamasarete Naku. ; Yaoi Behind the Screen ; Yuri on Livestream ; Yuri on Livestream, Yaoi Behind the Screen ; \uac70\uc9d3\ub9d0\uc7c1\uc774 \ubc31\ud569 \ub77c\uc774\ube0c ; \uac70\uc9d3\ub9d0\uc7c1\uc774 \ubc31\ud569 \ub77c\uc774\ube0c, \uba39\ud788\uba70 \uc6b8\ub2e4 ; \uba39\ud788\uba70 \uc6b8\ub2e4 ; \u5618\u3064\u304d\u767e\u5408\u914d\u4fe1\u3001\u3076\u3061\u304b\u307e\u3055\u308c\u3066\u6ce3\u304f\u3002",
  "authors": [
    "Hino Akimitsu",
    "Yaoi"
  ],
  "status": "Usotsuki Yuri Haishin, Buchikamasarete Naku. ; Yaoi Behind the Screen ; Yuri on Livestream ; Yuri on Livestream, Yaoi Behind the Screen ; \uac70\uc9d3\ub9d0\uc7c1\uc774 \ubc31\ud569 \ub77c\uc774\ube0c ; \uac70\uc9d3\ub9d0\uc7c1\uc774 \ubc31\ud569 \ub77c\uc774\ube0c, \uba39\ud788\uba70 \uc6b8\ub2e4 ; \uba39\ud788\uba70 \uc6b8\ub2e4 ; \u5618\u3064\u304d\u767e\u5408\u914d\u4fe1\u3001\u3076\u3061\u304b\u307e\u3055\u308c\u3066\u6ce3\u304f\u3002",
  "genres": [
    "Hino Akimitsu",
    "Yaoi"
  ],
  "updated_time": "Sep 26,2024 - 02:38 AM",
  "description": "Description :\r\n        \"Superchats make you feel better, right?\" Is this the start of a raw sex livestream between a gorgeous, high quality actor and a cold, lower class actor!?",
  "chapters": [
    {
      "chapter_name": "Chapter 3",
      "chapter_url": "https://chapmanganelo.com/manga-bv142115/chapter-3",
      "views": "12",
      "uploaded_time": "Sep 26,24"
    },
    {
      "chapter_name": "Chapter 2",
      "chapter_url": "https://chapmanganelo.com/manga-bv142115/chapter-2",
      "views": "11",
      "uploaded_time": "Sep 26,24"
    },
    {
      "chapter_name": "Chapter 1",
      "chapter_url": "https://chapmanganelo.com/manga-bv142115/chapter-1",
      "views": "12",
      "uploaded_time": "Sep 26,24"
    }
  ]
}