{
  "title": "Girl's World",
  "img": "https://avt.mkklcdnv6temp.com/fld/25/p/8-1732788880-nw.webp",
  "alternative_title": "Girl\u2019s World / Girl\u2019s World ( World of Girl ) / Odd Girl Out / \u5c11\u5973\u7684\u4e16\u754c (Chinese); \uc18c\ub140\uc758 \uc138\uacc4 (Korean)",
  "authors": [],
  "status": "Girl\u2019s World / Girl\u2019s World ( World of Girl ) / Odd Girl Out / \u5c11\u5973\u7684\u4e16\u754c (Chinese); \uc18c\ub140\uc758 \uc138\uacc4 (Korean)",
  "genres": [
    "Morangji",
    "Comedy",
    "Manhua",
    "Manhwa",
    "School life",
    "Shoujo",
    "Slice of life",
    "Webtoons"
  ],
  "updated_time": "Feb 11,2025 - 10:33 AM",
  "description": "Description :\r\n        It seems perfect, but in fact the lonely swans and the good-looking ducks meet and struggle with each other and become real friends ...",
  "chapters": [
    {
      "chapter_name": "Chapter 428: 427 - Part 2.212",
      "chapter_url": "https://chapmanganelo.com/manga-zg113826/chapter-428",
      "views": "1",
      "uploaded_time": "Feb 11,25"
    },
    {
      "chapter_name": "Chapter 427: 426 - Part 2.211",
      "chapter_url": "https://chapmanganelo.com/manga-zg113826/chapter-427",
      "views": "2",
      "uploaded_time": "Feb 04,25"
    },
    {
      "chapter_name": "Chapter 426: 425 - Part 2.210",
      "chapter_url": "https://chapmanganelo.com/manga-zg113826/chapter-426",
      "views": "2",
      "uploaded_time": "Jan 28,25"
    },
    {
      "chapter_name": "Chapter 425: 424 - Part 2.209",
      "chapter_url": "https://chapmanganelo.com/manga-zg113826/chapter-425",
      "views": "2",
      "uploaded_time": "Jan 21,25"
    },
    {
      "chapter_name": "Chapter 424: 423 - Part 2.208",
      "chapter_url": "https://chapmanganelo.com/manga-zg113826/chapter-424",
      "views": "2",
      "uploaded_time": "Jan 14,25"
    },
    {
      "chapter_name": "Chapter 423: 422 - Part 2.207",
      "chapter_url": "https://chapmanganelo.com/manga-zg113826/chapter-423",
      "views": "3",
      "uploaded_time": "Jan 07,25"
    },
    {
      "chapter_name": "Chapter 422: 421 - Part 2.206",
      "chapter_url": "https://chapmanganelo.com/manga-zg113826/chapter-422",
      "views": "3",
      "uploaded_time": "Dec 31,24"
    },
    {
      "chapter_name": "Chapter 421: 420 - Part 2.205",
      "chapter_url": "https://chapmanganelo.com/manga-zg113826/chapter-421",
      "views": "3",
      "uploaded_time": "Dec 24,24"
    },
    {
      "chapter_name": "Chapter 420: 419 - Part 2.204",
      "chapter_url": "https://chapmanganelo.com/manga-zg113826/chapter-420",
      "views": "4",
      "uploaded_time": "Dec 17,24"
    },
    {
      "chapter_name": "Chapter 419: 418 - Part 2.203",
      "chapter_url": "https://chapmanganelo.com/manga-zg113826/chapter-419",
      "views": "4",
      "uploaded_time": "Dec 10,24"
    },
    {
      "chapter_name": "Chapter 418: 417 - Part 2.202",
      "chapter_url": "https://chapmanganelo.com/manga-zg113826/chapter-418",
      "views": "3",
      "uploaded_time": "Dec 03,24"
    },
    {
      "chapter_name": "Chapter 417: 416 - Part 2.201",
      "chapter_url": "https://chapmanganelo.com/manga-zg113826/chapter-417",
      "views": "4",
      "uploaded_time": "Nov 26,24"
    },
    {
      "chapter_name": "Chapter 416: 415 - Part 2.200",
      "chapter_url": "https://chapmanganelo.com/manga-zg113826/chapter-416",
      "views": "4",
      "uploaded_time": "Nov 19,24"
    },
    {
      "chapter_name": "Chapter 415: 414 - Part 2.199",
      "chapter_url": "https://chapmanganelo.com/manga-zg113826/chapter-415",
      "views": "5",
      "uploaded_time": "Nov 12,24"
    },
    {
      "chapter_name": "Chapter 414: 413 - Part 2.198",
      "chapter_url": "https://chapmanganelo.com/manga-zg113826/chapter-414",
      "views": "4",
      "uploaded_time": "Nov 05,24"
    },
    {
      "chapter_name": "Chapter 413: 412 - Part 2.197",
      "chapter_url": "https://chapmanganelo.com/manga-zg113826/chapter-413",
      "views": "5",
      "uploaded_time": "Oct 29,24"
    },
    {
      "chapter_name": "Chapter 412: 411 - Part 2.196",
      "chapter_url": "https://chapmanganelo.com/manga-zg113826/chapter-412",
      "views": "5",
      "uploaded_time": "Oct 22,24"
    },
    {
      "chapter_name": "Chapter 411: 410 - Part 2.195",
      "chapter_url": "https://chapmanganelo.com/manga-zg113826/chapter-411",
      "views": "5",
      "uploaded_time": "Oct 15,24"
    },
    {
      "chapter_name": "Chapter 410: 409 - Part 2.194",
      "chapter_url": "https://chapmanganelo.com/manga-zg113826/chapter-410",
      "views": "5",
      "uploaded_time": "Oct 08,24"
    },
    {
      "chapter_name": "Chapter 409",
      "chapter_url": "https://chapmanganelo.com/manga-zg113826/chapter-409",
      "views": "6",
      "uploaded_time": "Oct 01,24"
    },
    {
      "chapter_name": "Chapter 408: 407 - Part 2.192",
      "chapter_url": "https://chapmanganelo.com/manga-zg113826/chapter-408",
      "views": "5",
      "uploaded_time": "Sep 24,24"
    },
    {
      "chapter_name": "Chapter 407: 406 - Part 2.191",
      "chapter_url": "https://chapmanganelo.com/manga-zg113826/chapter-407",
      "views": "5",
      "uploaded_time": "Sep 17,24"
    },
    {
      "chapter_name": "Chapter 406: 405 - Part 2.190",
      "chapter_url": "https://chapmanganelo.com/manga-zg113826/chapter-406",
      "views": "6",
      "uploaded_time": "Sep 10,24"
    },
    {
      "chapter_name": "Chapter 405: 404 - Part 2.189",
      "chapter_url": "https://chapmanganelo.com/manga-zg113826/chapter-405",
      "views": "6",
      "uploaded_time": "Sep 03,24"
    },
    {
      "chapter_name": "Chapter 404: 403 - Part 2.188",
      "chapter_url": "https://chapmanganelo.com/manga-zg113826/chapter-404",
      "views": "6",
      "uploaded_time": "Aug 27,24"
    },
    {
      "chapter_name": "Chapter 403: 402 - Part 2.187",
      "chapter_url": "https://chapmanganelo.com/manga-zg113826/chapter-403",
      "views": "7",
      "uploaded_time": "Aug 20,24"
    },
    {
      "chapter_name": "Chapter 402: 401 - Part 2.186",
      "chapter_url": "https://chapmanganelo.com/manga-zg113826/chapter-402",
      "views": "7",
      "uploaded_time": "Aug 13,24"
    },
    {
      "chapter_name": "Chapter 401: 400 - Part 2.185",
      "chapter_url": "https://chapmanganelo.com/manga-zg113826/chapter-401",
      "views": "7",
      "uploaded_time": "Aug 06,24"
    },
    {
      "chapter_name": "Chapter 400: 399 - Part 2.184",
      "chapter_url": "https://chapmanganelo.com/manga-zg113826/chapter-400",
      "views": "8",
      "uploaded_time": "Jul 30,24"
    },
    {
      "chapter_name": "Chapter 399: 398 - Part 2.183",
      "chapter_url": "https://chapmanganelo.com/manga-zg113826/chapter-399",
      "views": "7",
      "uploaded_time": "Jul 23,24"
    },
    {
      "chapter_name": "Chapter 398: 397 - Part 2.182",
      "chapter_url": "https://chapmanganelo.com/manga-zg113826/chapter-398",
      "views": "8",
      "uploaded_time": "Jul 16,24"
    },
    {
      "chapter_name": "Chapter 397: 396 - Part 2.181",
      "chapter_url": "https://chapmanganelo.com/manga-zg113826/chapter-397",
      "views": "7",
      "uploaded_time": "Jul 09,24"
    },
    {
      "chapter_name": "Chapter 396: 395 - Part 2.180",
      "chapter_url": "https://chapmanganelo.com/manga-zg113826/chapter-396",
      "views": "8",
      "uploaded_time": "Jul 02,24"
    },
    {
      "chapter_name": "Chapter 395: 394 - Part 2.179",
      "chapter_url": "https://chapmanganelo.com/manga-zg113826/chapter-395",
      "views": "8",
      "uploaded_time": "Jun 24,24"
    },
    {
      "chapter_name": "Chapter 394: 393 - Part 2.178",
      "chapter_url": "https://chapmanganelo.com/manga-zg113826/chapter-394",
      "views": "8",
      "uploaded_time": "Jun 18,24"
    },
    {
      "chapter_name": "Chapter 393: 392 - Part 2.177",
      "chapter_url": "https://chapmanganelo.com/manga-zg113826/chapter-393",
      "views": "8",
      "uploaded_time": "Jun 11,24"
    },
    {
      "chapter_name": "Chapter 392: 391 - Part 2.176",
      "chapter_url": "https://chapmanganelo.com/manga-zg113826/chapter-392",
      "views": "8",
      "uploaded_time": "Jun 04,24"
    },
    {
      "chapter_name": "Chapter 391: 390 - Part 2.175",
      "chapter_url": "https://chapmanganelo.com/manga-zg113826/chapter-391",
      "views": "9",
      "uploaded_time": "May 28,24"
    },
    {
      "chapter_name": "Chapter 390: 389 - Part 2.174",
      "chapter_url": "https://chapmanganelo.com/manga-zg113826/chapter-390",
      "views": "10",
      "uploaded_time": "May 21,24"
    },
    {
      "chapter_name": "Chapter 389: 388 - Part 2.173",
      "chapter_url": "https://chapmanganelo.com/manga-zg113826/chapter-389",
      "views": "10",
      "uploaded_time": "May 14,24"
    },
    {
      "chapter_name": "Chapter 388: 387 - Part 2.172",
      "chapter_url": "https://chapmanganelo.com/manga-zg113826/chapter-388",
      "views": "9",
      "uploaded_time": "May 07,24"
    },
    {
      "chapter_name": "Chapter 387: 386 - Part 2.171",
      "chapter_url": "https://chapmanganelo.com/manga-zg113826/chapter-387",
      "views": "8",
      "uploaded_time": "Apr 30,24"
    },
    {
      "chapter_name": "Chapter 386: 385 - Part 2.170",
      "chapter_url": "https://chapmanganelo.com/manga-zg113826/chapter-386",
      "views": "9",
      "uploaded_time": "Apr 23,24"
    },
    {
      "chapter_name": "Chapter 385: 384 - Part 2.169",
      "chapter_url": "https://chapmanganelo.com/manga-zg113826/chapter-385",
      "views": "10",
      "uploaded_time": "Apr 16,24"
    },
    {
      "chapter_name": "Chapter 384",
      "chapter_url": "https://chapmanganelo.com/manga-zg113826/chapter-384",
      "views": "9",
      "uploaded_time": "Apr 09,24"
    },
    {
      "chapter_name": "Chapter 383",
      "chapter_url": "https://chapmanganelo.com/manga-zg113826/chapter-383",
      "views": "11",
      "uploaded_time": "Apr 02,24"
    },
    {
      "chapter_name": "Chapter 382: 381 - Part 2.166",
      "chapter_url": "https://chapmanganelo.com/manga-zg113826/chapter-382",
      "views": "10",
      "uploaded_time": "Mar 26,24"
    },
    {
      "chapter_name": "Chapter 381: 380 - Part 2.165",
      "chapter_url": "https://chapmanganelo.com/manga-zg113826/chapter-381",
      "views": "11",
      "uploaded_time": "Mar 19,24"
    },
    {
      "chapter_name": "Chapter 380: 379 - Part 2.164",
      "chapter_url": "https://chapmanganelo.com/manga-zg113826/chapter-380",
      "views": "10",
      "uploaded_time": "Mar 12,24"
    },
    {
      "chapter_name": "Chapter 379: 378 - Part 2.163",
      "chapter_url": "https://chapmanganelo.com/manga-zg113826/chapter-379",
      "views": "10",
      "uploaded_time": "Mar 05,24"
    },
    {
      "chapter_name": "Chapter 378: 377 - Part 2.162",
      "chapter_url": "https://chapmanganelo.com/manga-zg113826/chapter-378",
      "views": "10",
      "uploaded_time": "Feb 27,24"
    },
    {
      "chapter_name": "Chapter 377: 376 - Part 2.161",
      "chapter_url": "https://chapmanganelo.com/manga-zg113826/chapter-377",
      "views": "11",
      "uploaded_time": "Feb 20,24"
    },
    {
      "chapter_name": "Chapter 376: 375 - Part 2.160",
      "chapter_url": "https://chapmanganelo.com/manga-zg113826/chapter-376",
      "views": "11",
      "uploaded_time": "Feb 13,24"
    },
    {
      "chapter_name": "Chapter 375: 374 - Part 2.159",
      "chapter_url": "https://chapmanganelo.com/manga-zg113826/chapter-375",
      "views": "11",
      "uploaded_time": "Feb 06,24"
    },
    {
      "chapter_name": "Chapter 374",
      "chapter_url": "https://chapmanganelo.com/manga-zg113826/chapter-374",
      "views": "12",
      "uploaded_time": "Jan 30,24"
    },
    {
      "chapter_name": "Chapter 373",
      "chapter_url": "https://chapmanganelo.com/manga-zg113826/chapter-373",
      "views": "10",
      "uploaded_time": "Jan 23,24"
    },
    {
      "chapter_name": "Chapter 372",
      "chapter_url": "https://chapmanganelo.com/manga-zg113826/chapter-372",
      "views": "12",
      "uploaded_time": "Jan 16,24"
    },
    {
      "chapter_name": "Chapter 371",
      "chapter_url": "https://chapmanganelo.com/manga-zg113826/chapter-371",
      "views": "12",
      "uploaded_time": "Jan 09,24"
    },
    {
      "chapter_name": "Chapter 370",
      "chapter_url": "https://chapmanganelo.com/manga-zg113826/chapter-370",
      "views": "13",
      "uploaded_time": "Jan 02,24"
    },
    {
      "chapter_name": "Chapter 369",
      "chapter_url": "https://chapmanganelo.com/manga-zg113826/chapter-369",
      "views": "11",
      "uploaded_time": "Dec 26,23"
    },
    {
      "chapter_name": "Chapter 368",
      "chapter_url": "https://chapmanganelo.com/manga-zg113826/chapter-368",
      "views": "11",
      "uploaded_time": "Dec 26,23"
    },
    {
      "chapter_name": "Chapter 367: 366 - Part 2.151",
      "chapter_url": "https://chapmanganelo.com/manga-zg113826/chapter-367",
      "views": "12",
      "uploaded_time": "Dec 12,23"
    },
    {
      "chapter_name": "Chapter 366: 365 - Part 2.150",
      "chapter_url": "https://chapmanganelo.com/manga-zg113826/chapter-366",
      "views": "12",
      "uploaded_time": "Dec 05,23"
    },
    {
      "chapter_name": "Chapter 365: 364 - Part 2.149",
      "chapter_url": "https://chapmanganelo.com/manga-zg113826/chapter-365",
      "views": "12",
      "uploaded_time": "Nov 28,23"
    },
    {
      "chapter_name": "Chapter 364: 363 - Part 2.148",
      "chapter_url": "https://chapmanganelo.com/manga-zg113826/chapter-364",
      "views": "12",
      "uploaded_time": "Nov 21,23"
    },
    {
      "chapter_name": "Chapter 363",
      "chapter_url": "https://chapmanganelo.com/manga-zg113826/chapter-363",
      "views": "12",
      "uploaded_time": "Nov 14,23"
    },
    {
      "chapter_name": "Chapter 362: 361 - Part 2.146",
      "chapter_url": "https://chapmanganelo.com/manga-zg113826/chapter-362",
      "views": "12",
      "uploaded_time": "Nov 07,23"
    },
    {
      "chapter_name": "Chapter 361: 360 - Part 2.145",
      "chapter_url": "https://chapmanganelo.com/manga-zg113826/chapter-361",
      "views": "12",
      "uploaded_time": "Oct 31,23"
    },
    {
      "chapter_name": "Chapter 360",
      "chapter_url": "https://chapmanganelo.com/manga-zg113826/chapter-360",
      "views": "13",
      "uploaded_time": "Oct 24,23"
    },
    {
      "chapter_name": "Chapter 359: 358 - Part 2.143",
      "chapter_url": "https://chapmanganelo.com/manga-zg113826/chapter-359",
      "views": "12",
      "uploaded_time": "Oct 17,23"
    },
    {
      "chapter_name": "Chapter 358",
      "chapter_url": "https://chapmanganelo.com/manga-zg113826/chapter-358",
      "views": "12",
      "uploaded_time": "Oct 10,23"
    },
    {
      "chapter_name": "Chapter 357: 356 - Part 2.141",
      "chapter_url": "https://chapmanganelo.com/manga-zg113826/chapter-357",
      "views": "12",
      "uploaded_time": "Oct 03,23"
    },
    {
      "chapter_name": "Chapter 356: 355 - Part 2.140",
      "chapter_url": "https://chapmanganelo.com/manga-zg113826/chapter-356",
      "views": "11",
      "uploaded_time": "Sep 26,23"
    },
    {
      "chapter_name": "Chapter 355",
      "chapter_url": "https://chapmanganelo.com/manga-zg113826/chapter-355",
      "views": "12",
      "uploaded_time": "Sep 19,23"
    },
    {
      "chapter_name": "Chapter 354",
      "chapter_url": "https://chapmanganelo.com/manga-zg113826/chapter-354",
      "views": "13",
      "uploaded_time": "Sep 12,23"
    },
    {
      "chapter_name": "Chapter 353",
      "chapter_url": "https://chapmanganelo.com/manga-zg113826/chapter-353",
      "views": "12",
      "uploaded_time": "Sep 05,23"
    },
    {
      "chapter_name": "Chapter 352: 351 - Part 2.136",
      "chapter_url": "https://chapmanganelo.com/manga-zg113826/chapter-352",
      "views": "12",
      "uploaded_time": "Aug 29,23"
    },
    {
      "chapter_name": "Chapter 351: 350 - Part 2.135",
      "chapter_url": "https://chapmanganelo.com/manga-zg113826/chapter-351",
      "views": "12",
      "uploaded_time": "Aug 22,23"
    },
    {
      "chapter_name": "Chapter 350: 349 - Part 2.134",
      "chapter_url": "https://chapmanganelo.com/manga-zg113826/chapter-350",
      "views": "13",
      "uploaded_time": "Aug 15,23"
    },
    {
      "chapter_name": "Chapter 349: 348 - Part 2.133",
      "chapter_url": "https://chapmanganelo.com/manga-zg113826/chapter-349",
      "views": "14",
      "uploaded_time": "Aug 08,23"
    },
    {
      "chapter_name": "Chapter 348: 347 - Part 2.132",
      "chapter_url": "https://chapmanganelo.com/manga-zg113826/chapter-348",
      "views": "14",
      "uploaded_time": "Aug 01,23"
    },
    {
      "chapter_name": "Chapter 347: 346 - Part 2.131",
      "chapter_url": "https://chapmanganelo.com/manga-zg113826/chapter-347",
      "views": "14",
      "uploaded_time": "Jul 25,23"
    },
    {
      "chapter_name": "Chapter 346: 345 - Part 2.130",
      "chapter_url": "https://chapmanganelo.com/manga-zg113826/chapter-346",
      "views": "13",
      "uploaded_time": "Jul 18,23"
    },
    {
      "chapter_name": "Chapter 345: 344 - Part 2.129",
      "chapter_url": "https://chapmanganelo.com/manga-zg113826/chapter-345",
      "views": "14",
      "uploaded_time": "Jul 11,23"
    },
    {
      "chapter_name": "Chapter 344",
      "chapter_url": "https://chapmanganelo.com/manga-zg113826/chapter-344",
      "views": "14",
      "uploaded_time": "Jul 04,23"
    },
    {
      "chapter_name": "Chapter 343: 342 - Part 2.127",
      "chapter_url": "https://chapmanganelo.com/manga-zg113826/chapter-343",
      "views": "13",
      "uploaded_time": "Jun 27,23"
    },
    {
      "chapter_name": "Chapter 342",
      "chapter_url": "https://chapmanganelo.com/manga-zg113826/chapter-342",
      "views": "13",
      "uploaded_time": "Jun 20,23"
    },
    {
      "chapter_name": "Chapter 341",
      "chapter_url": "https://chapmanganelo.com/manga-zg113826/chapter-341",
      "views": "12",
      "uploaded_time": "Jun 13,23"
    },
    {
      "chapter_name": "Chapter 340",
      "chapter_url": "https://chapmanganelo.com/manga-zg113826/chapter-340",
      "views": "14",
      "uploaded_time": "Jun 06,23"
    },
    {
      "chapter_name": "Chapter 339: 338 - Part 2.123",
      "chapter_url": "https://chapmanganelo.com/manga-zg113826/chapter-339",
      "views": "14",
      "uploaded_time": "May 30,23"
    },
    {
      "chapter_name": "Chapter 338: 337 - Part 2.122",
      "chapter_url": "https://chapmanganelo.com/manga-zg113826/chapter-338",
      "views": "14",
      "uploaded_time": "May 23,23"
    },
    {
      "chapter_name": "Chapter 337",
      "chapter_url": "https://chapmanganelo.com/manga-zg113826/chapter-337",
      "views": "30",
      "uploaded_time": "Nov 22,22"
    },
    {
      "chapter_name": "Chapter 336: 335 - Part 2.121",
      "chapter_url": "https://chapmanganelo.com/manga-zg113826/chapter-336",
      "views": "26",
      "uploaded_time": "Nov 15,22"
    },
    {
      "chapter_name": "Chapter 335: 334 - Part 2.120",
      "chapter_url": "https://chapmanganelo.com/manga-zg113826/chapter-335",
      "views": "26",
      "uploaded_time": "Nov 08,22"
    },
    {
      "chapter_name": "Chapter 334: 333 - Part 2.119",
      "chapter_url": "https://chapmanganelo.com/manga-zg113826/chapter-334",
      "views": "28",
      "uploaded_time": "Nov 01,22"
    },
    {
      "chapter_name": "Chapter 333 - 332",
      "chapter_url": "https://chapmanganelo.com/manga-zg113826/chapter-333",
      "views": "27",
      "uploaded_time": "Oct 25,22"
    },
    {
      "chapter_name": "Chapter 332",
      "chapter_url": "https://chapmanganelo.com/manga-zg113826/chapter-332",
      "views": "18",
      "uploaded_time": "Oct 18,22"
    },
    {
      "chapter_name": "Chapter 331",
      "chapter_url": "https://chapmanganelo.com/manga-zg113826/chapter-331",
      "views": "18",
      "uploaded_time": "Oct 11,22"
    },
    {
      "chapter_name": "Chapter 330: 329 - Part 2.115",
      "chapter_url": "https://chapmanganelo.com/manga-zg113826/chapter-330",
      "views": "18",
      "uploaded_time": "Oct 04,22"
    },
    {
      "chapter_name": "Chapter 329: 328 - Part 2.114",
      "chapter_url": "https://chapmanganelo.com/manga-zg113826/chapter-329",
      "views": "19",
      "uploaded_time": "Sep 27,22"
    },
    {
      "chapter_name": "Chapter 328",
      "chapter_url": "https://chapmanganelo.com/manga-zg113826/chapter-328",
      "views": "20",
      "uploaded_time": "Sep 20,22"
    },
    {
      "chapter_name": "Chapter 327: 326 - Part 2.112",
      "chapter_url": "https://chapmanganelo.com/manga-zg113826/chapter-327",
      "views": "17",
      "uploaded_time": "Sep 13,22"
    },
    {
      "chapter_name": "Chapter 326: 325 - Part 2.111",
      "chapter_url": "https://chapmanganelo.com/manga-zg113826/chapter-326",
      "views": "17",
      "uploaded_time": "Sep 06,22"
    },
    {
      "chapter_name": "Chapter 325: 324 - Part 2.110",
      "chapter_url": "https://chapmanganelo.com/manga-zg113826/chapter-325",
      "views": "18",
      "uploaded_time": "Aug 30,22"
    },
    {
      "chapter_name": "Chapter 324: 323 - Part 2.109",
      "chapter_url": "https://chapmanganelo.com/manga-zg113826/chapter-324",
      "views": "19",
      "uploaded_time": "Aug 23,22"
    },
    {
      "chapter_name": "Chapter 323 - 322",
      "chapter_url": "https://chapmanganelo.com/manga-zg113826/chapter-323",
      "views": "18",
      "uploaded_time": "Aug 16,22"
    },
    {
      "chapter_name": "Chapter 322",
      "chapter_url": "https://chapmanganelo.com/manga-zg113826/chapter-322",
      "views": "18",
      "uploaded_time": "Aug 09,22"
    },
    {
      "chapter_name": "Chapter 321: 320 - Part 2.106",
      "chapter_url": "https://chapmanganelo.com/manga-zg113826/chapter-321",
      "views": "18",
      "uploaded_time": "Aug 02,22"
    },
    {
      "chapter_name": "Chapter 320: 319 - Part 2.105",
      "chapter_url": "https://chapmanganelo.com/manga-zg113826/chapter-320",
      "views": "18",
      "uploaded_time": "Jul 26,22"
    },
    {
      "chapter_name": "Chapter 319 - 318",
      "chapter_url": "https://chapmanganelo.com/manga-zg113826/chapter-319",
      "views": "20",
      "uploaded_time": "Jul 19,22"
    },
    {
      "chapter_name": "Chapter 318: 317 - Part 2.103",
      "chapter_url": "https://chapmanganelo.com/manga-zg113826/chapter-318",
      "views": "18",
      "uploaded_time": "Jul 12,22"
    },
    {
      "chapter_name": "Chapter 317: 316 - Part 2.102",
      "chapter_url": "https://chapmanganelo.com/manga-zg113826/chapter-317",
      "views": "19",
      "uploaded_time": "Jul 05,22"
    },
    {
      "chapter_name": "Chapter 316: 315 - Part 2.101",
      "chapter_url": "https://chapmanganelo.com/manga-zg113826/chapter-316",
      "views": "17",
      "uploaded_time": "Jun 28,22"
    },
    {
      "chapter_name": "Chapter 315: 314 - Part 2.100",
      "chapter_url": "https://chapmanganelo.com/manga-zg113826/chapter-315",
      "views": "18",
      "uploaded_time": "Jun 21,22"
    },
    {
      "chapter_name": "Chapter 314: 313 - Part 2.99",
      "chapter_url": "https://chapmanganelo.com/manga-zg113826/chapter-314",
      "views": "19",
      "uploaded_time": "Jun 14,22"
    },
    {
      "chapter_name": "Chapter 313: 312 - Part 2.98",
      "chapter_url": "https://chapmanganelo.com/manga-zg113826/chapter-313",
      "views": "20",
      "uploaded_time": "Jun 07,22"
    },
    {
      "chapter_name": "Chapter 312: 311 - Part 2.97",
      "chapter_url": "https://chapmanganelo.com/manga-zg113826/chapter-312",
      "views": "20",
      "uploaded_time": "May 31,22"
    },
    {
      "chapter_name": "Chapter 311: 310 - Part 2.96",
      "chapter_url": "https://chapmanganelo.com/manga-zg113826/chapter-311",
      "views": "23",
      "uploaded_time": "May 24,22"
    },
    {
      "chapter_name": "Chapter 310: 309 - Part 2.95",
      "chapter_url": "https://chapmanganelo.com/manga-zg113826/chapter-310",
      "views": "23",
      "uploaded_time": "May 17,22"
    },
    {
      "chapter_name": "Chapter 309: 308 - Part 2.94",
      "chapter_url": "https://chapmanganelo.com/manga-zg113826/chapter-309",
      "views": "23",
      "uploaded_time": "May 10,22"
    },
    {
      "chapter_name": "Chapter 308: 307 - Part 2.93",
      "chapter_url": "https://chapmanganelo.com/manga-zg113826/chapter-308",
      "views": "24",
      "uploaded_time": "May 03,22"
    },
    {
      "chapter_name": "Chapter 307: 306 - Part 2.92",
      "chapter_url": "https://chapmanganelo.com/manga-zg113826/chapter-307",
      "views": "23",
      "uploaded_time": "Apr 26,22"
    },
    {
      "chapter_name": "Chapter 306: 305 - Part 2.91",
      "chapter_url": "https://chapmanganelo.com/manga-zg113826/chapter-306",
      "views": "24",
      "uploaded_time": "Apr 19,22"
    },
    {
      "chapter_name": "Chapter 305: 304 - Part 2.90",
      "chapter_url": "https://chapmanganelo.com/manga-zg113826/chapter-305",
      "views": "24",
      "uploaded_time": "Apr 12,22"
    },
    {
      "chapter_name": "Chapter 304: 303 - Part 2.89",
      "chapter_url": "https://chapmanganelo.com/manga-zg113826/chapter-304",
      "views": "24",
      "uploaded_time": "Apr 05,22"
    },
    {
      "chapter_name": "Chapter 303: 302 - Part 2.88",
      "chapter_url": "https://chapmanganelo.com/manga-zg113826/chapter-303",
      "views": "24",
      "uploaded_time": "Mar 29,22"
    },
    {
      "chapter_name": "Chapter 302: 301 - Part 2.87",
      "chapter_url": "https://chapmanganelo.com/manga-zg113826/chapter-302",
      "views": "24",
      "uploaded_time": "Mar 22,22"
    },
    {
      "chapter_name": "Chapter 301: 300 - Part 2.86",
      "chapter_url": "https://chapmanganelo.com/manga-zg113826/chapter-301",
      "views": "24",
      "uploaded_time": "Mar 15,22"
    },
    {
      "chapter_name": "Chapter 300: 299 - Part 2.85",
      "chapter_url": "https://chapmanganelo.com/manga-zg113826/chapter-300",
      "views": "24",
      "uploaded_time": "Mar 08,22"
    },
    {
      "chapter_name": "Chapter 299: 298 - Part 2.84",
      "chapter_url": "https://chapmanganelo.com/manga-zg113826/chapter-299",
      "views": "25",
      "uploaded_time": "Mar 01,22"
    },
    {
      "chapter_name": "Chapter 298: Special Episode",
      "chapter_url": "https://chapmanganelo.com/manga-zg113826/chapter-298",
      "views": "21",
      "uploaded_time": "Mar 01,22"
    },
    {
      "chapter_name": "Chapter 297: 297 - Part 2.83",
      "chapter_url": "https://chapmanganelo.com/manga-zg113826/chapter-297",
      "views": "25",
      "uploaded_time": "Feb 15,22"
    },
    {
      "chapter_name": "Chapter 296: 296 - Part 2.82",
      "chapter_url": "https://chapmanganelo.com/manga-zg113826/chapter-296",
      "views": "25",
      "uploaded_time": "Feb 08,22"
    },
    {
      "chapter_name": "Chapter 295: 295 - Part 2.81",
      "chapter_url": "https://chapmanganelo.com/manga-zg113826/chapter-295",
      "views": "23",
      "uploaded_time": "Feb 01,22"
    },
    {
      "chapter_name": "Chapter 294: 294 - Part 2.80",
      "chapter_url": "https://chapmanganelo.com/manga-zg113826/chapter-294",
      "views": "25",
      "uploaded_time": "Jan 25,22"
    },
    {
      "chapter_name": "Chapter 293",
      "chapter_url": "https://chapmanganelo.com/manga-zg113826/chapter-293",
      "views": "25",
      "uploaded_time": "Jan 04,22"
    },
    {
      "chapter_name": "Chapter 292",
      "chapter_url": "https://chapmanganelo.com/manga-zg113826/chapter-292",
      "views": "23",
      "uploaded_time": "Jan 04,22"
    },
    {
      "chapter_name": "Chapter 291: 291 - Part 2.77",
      "chapter_url": "https://chapmanganelo.com/manga-zg113826/chapter-291",
      "views": "25",
      "uploaded_time": "Jan 04,22"
    },
    {
      "chapter_name": "Chapter 290: 290 - Part 2.76",
      "chapter_url": "https://chapmanganelo.com/manga-zg113826/chapter-290",
      "views": "26",
      "uploaded_time": "Dec 28,21"
    },
    {
      "chapter_name": "Chapter 289: 289 - Part 2.75",
      "chapter_url": "https://chapmanganelo.com/manga-zg113826/chapter-289",
      "views": "26",
      "uploaded_time": "Dec 21,21"
    },
    {
      "chapter_name": "Chapter 288: 288 - Part 2.74",
      "chapter_url": "https://chapmanganelo.com/manga-zg113826/chapter-288",
      "views": "26",
      "uploaded_time": "Dec 14,21"
    },
    {
      "chapter_name": "Chapter 287: 287 - Part 2.73",
      "chapter_url": "https://chapmanganelo.com/manga-zg113826/chapter-287",
      "views": "25",
      "uploaded_time": "Dec 07,21"
    },
    {
      "chapter_name": "Chapter 286: 286 - Part 2.72",
      "chapter_url": "https://chapmanganelo.com/manga-zg113826/chapter-286",
      "views": "25",
      "uploaded_time": "Nov 30,21"
    },
    {
      "chapter_name": "Chapter 285: 285 - Part 2.71",
      "chapter_url": "https://chapmanganelo.com/manga-zg113826/chapter-285",
      "views": "25",
      "uploaded_time": "Nov 23,21"
    },
    {
      "chapter_name": "Chapter 284: 284 - Part 2.70",
      "chapter_url": "https://chapmanganelo.com/manga-zg113826/chapter-284",
      "views": "26",
      "uploaded_time": "Nov 16,21"
    },
    {
      "chapter_name": "Chapter 283: 283 - Part 2.69",
      "chapter_url": "https://chapmanganelo.com/manga-zg113826/chapter-283",
      "views": "23",
      "uploaded_time": "Nov 09,21"
    },
    {
      "chapter_name": "Chapter 282: 282 - Part 2.68",
      "chapter_url": "https://chapmanganelo.com/manga-zg113826/chapter-282",
      "views": "25",
      "uploaded_time": "Nov 02,21"
    },
    {
      "chapter_name": "Chapter 281: 281 - Part 2.67",
      "chapter_url": "https://chapmanganelo.com/manga-zg113826/chapter-281",
      "views": "25",
      "uploaded_time": "Oct 26,21"
    },
    {
      "chapter_name": "Chapter 280: 280 - Part 2.66",
      "chapter_url": "https://chapmanganelo.com/manga-zg113826/chapter-280",
      "views": "27",
      "uploaded_time": "Oct 19,21"
    },
    {
      "chapter_name": "Chapter 279: 279 - Part 2.65",
      "chapter_url": "https://chapmanganelo.com/manga-zg113826/chapter-279",
      "views": "26",
      "uploaded_time": "Oct 12,21"
    },
    {
      "chapter_name": "Chapter 278: 278 - Part 2.64",
      "chapter_url": "https://chapmanganelo.com/manga-zg113826/chapter-278",
      "views": "27",
      "uploaded_time": "Oct 05,21"
    },
    {
      "chapter_name": "Chapter 277: 277 - Part 2.63",
      "chapter_url": "https://chapmanganelo.com/manga-zg113826/chapter-277",
      "views": "27",
      "uploaded_time": "Sep 28,21"
    },
    {
      "chapter_name": "Chapter 276: 276 - Part 2.62",
      "chapter_url": "https://chapmanganelo.com/manga-zg113826/chapter-276",
      "views": "25",
      "uploaded_time": "Sep 28,21"
    },
    {
      "chapter_name": "Chapter 275: 275 - Part 2.61",
      "chapter_url": "https://chapmanganelo.com/manga-zg113826/chapter-275",
      "views": "27",
      "uploaded_time": "Sep 14,21"
    },
    {
      "chapter_name": "Chapter 274: 274 - Part 2.60",
      "chapter_url": "https://chapmanganelo.com/manga-zg113826/chapter-274",
      "views": "27",
      "uploaded_time": "Sep 07,21"
    },
    {
      "chapter_name": "Chapter 273: 273 - Part 2.59",
      "chapter_url": "https://chapmanganelo.com/manga-zg113826/chapter-273",
      "views": "26",
      "uploaded_time": "Aug 31,21"
    },
    {
      "chapter_name": "Chapter 272: 272 - Part 2.58",
      "chapter_url": "https://chapmanganelo.com/manga-zg113826/chapter-272",
      "views": "27",
      "uploaded_time": "Aug 24,21"
    },
    {
      "chapter_name": "Chapter 271: 271 - Part 2.57",
      "chapter_url": "https://chapmanganelo.com/manga-zg113826/chapter-271",
      "views": "27",
      "uploaded_time": "Aug 17,21"
    },
    {
      "chapter_name": "Chapter 270: 270 - Part 2.56",
      "chapter_url": "https://chapmanganelo.com/manga-zg113826/chapter-270",
      "views": "27",
      "uploaded_time": "Aug 10,21"
    },
    {
      "chapter_name": "Chapter 269: 269 - Part 2.55",
      "chapter_url": "https://chapmanganelo.com/manga-zg113826/chapter-269",
      "views": "29",
      "uploaded_time": "Aug 03,21"
    },
    {
      "chapter_name": "Chapter 268: 268 - Part 2.54",
      "chapter_url": "https://chapmanganelo.com/manga-zg113826/chapter-268",
      "views": "28",
      "uploaded_time": "Jul 27,21"
    },
    {
      "chapter_name": "Chapter 267: 267 - Part 2.53",
      "chapter_url": "https://chapmanganelo.com/manga-zg113826/chapter-267",
      "views": "29",
      "uploaded_time": "Jul 20,21"
    },
    {
      "chapter_name": "Chapter 266: 266 - Part 2.52",
      "chapter_url": "https://chapmanganelo.com/manga-zg113826/chapter-266",
      "views": "29",
      "uploaded_time": "Jul 13,21"
    },
    {
      "chapter_name": "Chapter 265: 265 - Part 2.51",
      "chapter_url": "https://chapmanganelo.com/manga-zg113826/chapter-265",
      "views": "30",
      "uploaded_time": "Jul 06,21"
    },
    {
      "chapter_name": "Chapter 264: 264 - Part 2.50",
      "chapter_url": "https://chapmanganelo.com/manga-zg113826/chapter-264",
      "views": "30",
      "uploaded_time": "Jun 29,21"
    },
    {
      "chapter_name": "Chapter 263: 263 - Part 2.49",
      "chapter_url": "https://chapmanganelo.com/manga-zg113826/chapter-263",
      "views": "30",
      "uploaded_time": "Jun 22,21"
    },
    {
      "chapter_name": "Chapter 262: 262 - Part 2.48",
      "chapter_url": "https://chapmanganelo.com/manga-zg113826/chapter-262",
      "views": "29",
      "uploaded_time": "Jun 15,21"
    },
    {
      "chapter_name": "Chapter 261: 261 - Part 2.47",
      "chapter_url": "https://chapmanganelo.com/manga-zg113826/chapter-261",
      "views": "31",
      "uploaded_time": "Jun 08,21"
    },
    {
      "chapter_name": "Chapter 260: 260 - Part 2.46",
      "chapter_url": "https://chapmanganelo.com/manga-zg113826/chapter-260",
      "views": "31",
      "uploaded_time": "Jun 01,21"
    },
    {
      "chapter_name": "Chapter 259: 259 - Part 2.45",
      "chapter_url": "https://chapmanganelo.com/manga-zg113826/chapter-259",
      "views": "30",
      "uploaded_time": "May 25,21"
    },
    {
      "chapter_name": "Chapter 258: 258 - Part 2.44",
      "chapter_url": "https://chapmanganelo.com/manga-zg113826/chapter-258",
      "views": "32",
      "uploaded_time": "May 18,21"
    },
    {
      "chapter_name": "Chapter 257: 257 - Part 2.43",
      "chapter_url": "https://chapmanganelo.com/manga-zg113826/chapter-257",
      "views": "31",
      "uploaded_time": "May 11,21"
    },
    {
      "chapter_name": "Chapter 256: 256 - Part 2.42",
      "chapter_url": "https://chapmanganelo.com/manga-zg113826/chapter-256",
      "views": "31",
      "uploaded_time": "May 04,21"
    },
    {
      "chapter_name": "Chapter 255: 255 - Part 2.41",
      "chapter_url": "https://chapmanganelo.com/manga-zg113826/chapter-255",
      "views": "29",
      "uploaded_time": "Apr 27,21"
    },
    {
      "chapter_name": "Chapter 254: 254 - Part 2.40",
      "chapter_url": "https://chapmanganelo.com/manga-zg113826/chapter-254",
      "views": "31",
      "uploaded_time": "Apr 20,21"
    },
    {
      "chapter_name": "Chapter 253: 253 - Part 2.39",
      "chapter_url": "https://chapmanganelo.com/manga-zg113826/chapter-253",
      "views": "31",
      "uploaded_time": "Apr 13,21"
    },
    {
      "chapter_name": "Chapter 252: 252 - Part 2.38",
      "chapter_url": "https://chapmanganelo.com/manga-zg113826/chapter-252",
      "views": "29",
      "uploaded_time": "Apr 06,21"
    },
    {
      "chapter_name": "Chapter 251: 251 - Part 2.37",
      "chapter_url": "https://chapmanganelo.com/manga-zg113826/chapter-251",
      "views": "28",
      "uploaded_time": "Mar 30,21"
    },
    {
      "chapter_name": "Chapter 250: 250 - Part 2.36",
      "chapter_url": "https://chapmanganelo.com/manga-zg113826/chapter-250",
      "views": "29",
      "uploaded_time": "Mar 23,21"
    },
    {
      "chapter_name": "Chapter 249: 249 - Part 2.35",
      "chapter_url": "https://chapmanganelo.com/manga-zg113826/chapter-249",
      "views": "24",
      "uploaded_time": "Mar 23,21"
    },
    {
      "chapter_name": "Chapter 248: 248 - Part 2.34",
      "chapter_url": "https://chapmanganelo.com/manga-zg113826/chapter-248",
      "views": "26",
      "uploaded_time": "Mar 09,21"
    },
    {
      "chapter_name": "Chapter 247: 247 - Part 2.33",
      "chapter_url": "https://chapmanganelo.com/manga-zg113826/chapter-247",
      "views": "24",
      "uploaded_time": "Mar 02,21"
    },
    {
      "chapter_name": "Chapter 246: 246 - Part 2.32",
      "chapter_url": "https://chapmanganelo.com/manga-zg113826/chapter-246",
      "views": "21",
      "uploaded_time": "Feb 23,21"
    },
    {
      "chapter_name": "Chapter 245: 245 - Part 2.31",
      "chapter_url": "https://chapmanganelo.com/manga-zg113826/chapter-245",
      "views": "21",
      "uploaded_time": "Feb 16,21"
    },
    {
      "chapter_name": "Chapter 244: 244 - Part 2.30",
      "chapter_url": "https://chapmanganelo.com/manga-zg113826/chapter-244",
      "views": "21",
      "uploaded_time": "Feb 09,21"
    },
    {
      "chapter_name": "Chapter 243: 243 - Part 2.29",
      "chapter_url": "https://chapmanganelo.com/manga-zg113826/chapter-243",
      "views": "21",
      "uploaded_time": "Feb 02,21"
    },
    {
      "chapter_name": "Chapter 242: 242 - Part 2.28",
      "chapter_url": "https://chapmanganelo.com/manga-zg113826/chapter-242",
      "views": "22",
      "uploaded_time": "Jan 26,21"
    },
    {
      "chapter_name": "Chapter 241: 241 - Part 2.27",
      "chapter_url": "https://chapmanganelo.com/manga-zg113826/chapter-241",
      "views": "22",
      "uploaded_time": "Jan 19,21"
    },
    {
      "chapter_name": "Chapter 240: 240 - Part 2.26",
      "chapter_url": "https://chapmanganelo.com/manga-zg113826/chapter-240",
      "views": "23",
      "uploaded_time": "Jan 12,21"
    },
    {
      "chapter_name": "Chapter 239: 239 - Part 2.25",
      "chapter_url": "https://chapmanganelo.com/manga-zg113826/chapter-239",
      "views": "23",
      "uploaded_time": "Jan 05,21"
    },
    {
      "chapter_name": "Chapter 238: 238 - Part 2.24",
      "chapter_url": "https://chapmanganelo.com/manga-zg113826/chapter-238",
      "views": "22",
      "uploaded_time": "Dec 29,20"
    },
    {
      "chapter_name": "Chapter 237: 237 - Part 2.23",
      "chapter_url": "https://chapmanganelo.com/manga-zg113826/chapter-237",
      "views": "20",
      "uploaded_time": "Dec 22,20"
    },
    {
      "chapter_name": "Chapter 236",
      "chapter_url": "https://chapmanganelo.com/manga-zg113826/chapter-236",
      "views": "20",
      "uploaded_time": "Dec 16,20"
    },
    {
      "chapter_name": "Chapter 235: 235 - Part 2.21",
      "chapter_url": "https://chapmanganelo.com/manga-zg113826/chapter-235",
      "views": "21",
      "uploaded_time": "Dec 08,20"
    },
    {
      "chapter_name": "Chapter 234: 234 - Part 2.20",
      "chapter_url": "https://chapmanganelo.com/manga-zg113826/chapter-234",
      "views": "19",
      "uploaded_time": "Dec 01,20"
    },
    {
      "chapter_name": "Chapter 233: 233 - Part 2.19",
      "chapter_url": "https://chapmanganelo.com/manga-zg113826/chapter-233",
      "views": "19",
      "uploaded_time": "Nov 24,20"
    },
    {
      "chapter_name": "Chapter 232: 232 - Part 2.18",
      "chapter_url": "https://chapmanganelo.com/manga-zg113826/chapter-232",
      "views": "20",
      "uploaded_time": "Nov 17,20"
    },
    {
      "chapter_name": "Chapter 231: 231 - Part 2.17",
      "chapter_url": "https://chapmanganelo.com/manga-zg113826/chapter-231",
      "views": "20",
      "uploaded_time": "Nov 10,20"
    },
    {
      "chapter_name": "Chapter 230: 230 - Part 2.16",
      "chapter_url": "https://chapmanganelo.com/manga-zg113826/chapter-230",
      "views": "20",
      "uploaded_time": "Nov 03,20"
    },
    {
      "chapter_name": "Chapter 229: 229 - Part 2.15",
      "chapter_url": "https://chapmanganelo.com/manga-zg113826/chapter-229",
      "views": "21",
      "uploaded_time": "Oct 27,20"
    },
    {
      "chapter_name": "Chapter 228: 228 - Part 2.14",
      "chapter_url": "https://chapmanganelo.com/manga-zg113826/chapter-228",
      "views": "19",
      "uploaded_time": "Oct 27,20"
    },
    {
      "chapter_name": "Chapter 227: 227 - Part 2.13",
      "chapter_url": "https://chapmanganelo.com/manga-zg113826/chapter-227",
      "views": "20",
      "uploaded_time": "Oct 13,20"
    },
    {
      "chapter_name": "Chapter 226: 226 - Part 2.12",
      "chapter_url": "https://chapmanganelo.com/manga-zg113826/chapter-226",
      "views": "20",
      "uploaded_time": "Oct 06,20"
    },
    {
      "chapter_name": "Chapter 225: 225 - Part 2.11",
      "chapter_url": "https://chapmanganelo.com/manga-zg113826/chapter-225",
      "views": "20",
      "uploaded_time": "Sep 29,20"
    },
    {
      "chapter_name": "Chapter 224: 224 - Part 2.10",
      "chapter_url": "https://chapmanganelo.com/manga-zg113826/chapter-224",
      "views": "20",
      "uploaded_time": "Sep 22,20"
    },
    {
      "chapter_name": "Chapter 223: 223 - Part 2.9",
      "chapter_url": "https://chapmanganelo.com/manga-zg113826/chapter-223",
      "views": "20",
      "uploaded_time": "Sep 15,20"
    },
    {
      "chapter_name": "Chapter 222: 222 - Part 2.8",
      "chapter_url": "https://chapmanganelo.com/manga-zg113826/chapter-222",
      "views": "20",
      "uploaded_time": "Sep 08,20"
    },
    {
      "chapter_name": "Chapter 221: 221 - Part 2.7",
      "chapter_url": "https://chapmanganelo.com/manga-zg113826/chapter-221",
      "views": "21",
      "uploaded_time": "Sep 01,20"
    },
    {
      "chapter_name": "Chapter 220: 220 - Part 2.6",
      "chapter_url": "https://chapmanganelo.com/manga-zg113826/chapter-220",
      "views": "21",
      "uploaded_time": "Aug 25,20"
    },
    {
      "chapter_name": "Chapter 219: 219 - Part 2.5",
      "chapter_url": "https://chapmanganelo.com/manga-zg113826/chapter-219",
      "views": "20",
      "uploaded_time": "Aug 18,20"
    },
    {
      "chapter_name": "Chapter 218: 218 - Part 2.4",
      "chapter_url": "https://chapmanganelo.com/manga-zg113826/chapter-218",
      "views": "22",
      "uploaded_time": "Aug 11,20"
    },
    {
      "chapter_name": "Chapter 217: 217 - Part 2.3",
      "chapter_url": "https://chapmanganelo.com/manga-zg113826/chapter-217",
      "views": "21",
      "uploaded_time": "Aug 04,20"
    },
    {
      "chapter_name": "Chapter 216: 216 - Part 2.2",
      "chapter_url": "https://chapmanganelo.com/manga-zg113826/chapter-216",
      "views": "21",
      "uploaded_time": "Jul 28,20"
    },
    {
      "chapter_name": "Chapter 215: 215 - Part 2.1",
      "chapter_url": "https://chapmanganelo.com/manga-zg113826/chapter-215",
      "views": "23",
      "uploaded_time": "Jul 21,20"
    },
    {
      "chapter_name": "Chapter 214: 214 - Part 2 - Prologue",
      "chapter_url": "https://chapmanganelo.com/manga-zg113826/chapter-214",
      "views": "20",
      "uploaded_time": "Jul 14,20"
    },
    {
      "chapter_name": "Chapter 213: 213 - Nari's Letter",
      "chapter_url": "https://chapmanganelo.com/manga-zg113826/chapter-213",
      "views": "20",
      "uploaded_time": "Jul 07,20"
    },
    {
      "chapter_name": "Chapter 212: 212 - Until We Meet Again",
      "chapter_url": "https://chapmanganelo.com/manga-zg113826/chapter-212",
      "views": "20",
      "uploaded_time": "Jun 30,20"
    },
    {
      "chapter_name": "Chapter 211: 211 - This Time...",
      "chapter_url": "https://chapmanganelo.com/manga-zg113826/chapter-211",
      "views": "20",
      "uploaded_time": "Jun 23,20"
    },
    {
      "chapter_name": "Chapter 210: 210 - Different Dreams (2)",
      "chapter_url": "https://chapmanganelo.com/manga-zg113826/chapter-210",
      "views": "18",
      "uploaded_time": "Jun 16,20"
    },
    {
      "chapter_name": "Chapter 209: 209 - Dreaming Different Dreams",
      "chapter_url": "https://chapmanganelo.com/manga-zg113826/chapter-209",
      "views": "19",
      "uploaded_time": "Jun 09,20"
    },
    {
      "chapter_name": "Chapter 208: 208 - Yuna's Birthday",
      "chapter_url": "https://chapmanganelo.com/manga-zg113826/chapter-208",
      "views": "20",
      "uploaded_time": "Jun 02,20"
    },
    {
      "chapter_name": "Chapter 207: 207 - Trip 4",
      "chapter_url": "https://chapmanganelo.com/manga-zg113826/chapter-207",
      "views": "22",
      "uploaded_time": "May 26,20"
    },
    {
      "chapter_name": "Chapter 206: 206 - Trip 3",
      "chapter_url": "https://chapmanganelo.com/manga-zg113826/chapter-206",
      "views": "20",
      "uploaded_time": "May 19,20"
    },
    {
      "chapter_name": "Chapter 205: 205 - Trip 2",
      "chapter_url": "https://chapmanganelo.com/manga-zg113826/chapter-205",
      "views": "20",
      "uploaded_time": "May 12,20"
    },
    {
      "chapter_name": "Chapter 204: 204 - Trip",
      "chapter_url": "https://chapmanganelo.com/manga-zg113826/chapter-204",
      "views": "21",
      "uploaded_time": "May 05,20"
    },
    {
      "chapter_name": "Chapter 203: 203 - A Birthday Gift For Yuna",
      "chapter_url": "https://chapmanganelo.com/manga-zg113826/chapter-203",
      "views": "21",
      "uploaded_time": "May 05,20"
    },
    {
      "chapter_name": "Chapter 202: 202 - Winter Break",
      "chapter_url": "https://chapmanganelo.com/manga-zg113826/chapter-202",
      "views": "21",
      "uploaded_time": "Apr 21,20"
    },
    {
      "chapter_name": "Chapter 201: 201 - Wrap Party (4)",
      "chapter_url": "https://chapmanganelo.com/manga-zg113826/chapter-201",
      "views": "21",
      "uploaded_time": "Apr 14,20"
    },
    {
      "chapter_name": "Chapter 200: 200 - Wrap Party (3)",
      "chapter_url": "https://chapmanganelo.com/manga-zg113826/chapter-200",
      "views": "21",
      "uploaded_time": "Apr 07,20"
    },
    {
      "chapter_name": "Chapter 199: 199 - Wrap Party (2)",
      "chapter_url": "https://chapmanganelo.com/manga-zg113826/chapter-199",
      "views": "21",
      "uploaded_time": "Mar 31,20"
    },
    {
      "chapter_name": "Chapter 198: 198 - Wrap Party",
      "chapter_url": "https://chapmanganelo.com/manga-zg113826/chapter-198",
      "views": "21",
      "uploaded_time": "Mar 24,20"
    },
    {
      "chapter_name": "Chapter 197: 197 - Dreams Do Come True (Mirae's Perspective) (2)",
      "chapter_url": "https://chapmanganelo.com/manga-zg113826/chapter-197",
      "views": "22",
      "uploaded_time": "Mar 17,20"
    },
    {
      "chapter_name": "Chapter 196: 196 - Dreams Do Come True (Mirae's Perspective)",
      "chapter_url": "https://chapmanganelo.com/manga-zg113826/chapter-196",
      "views": "22",
      "uploaded_time": "Mar 10,20"
    },
    {
      "chapter_name": "Chapter 195",
      "chapter_url": "https://chapmanganelo.com/manga-zg113826/chapter-195",
      "views": "22",
      "uploaded_time": "Mar 04,20"
    },
    {
      "chapter_name": "Chapter 194",
      "chapter_url": "https://chapmanganelo.com/manga-zg113826/chapter-194",
      "views": "21",
      "uploaded_time": "Feb 26,20"
    },
    {
      "chapter_name": "Chapter 193",
      "chapter_url": "https://chapmanganelo.com/manga-zg113826/chapter-193",
      "views": "20",
      "uploaded_time": "Feb 26,20"
    },
    {
      "chapter_name": "Chapter 192",
      "chapter_url": "https://chapmanganelo.com/manga-zg113826/chapter-192",
      "views": "20",
      "uploaded_time": "Feb 26,20"
    },
    {
      "chapter_name": "Chapter 191",
      "chapter_url": "https://chapmanganelo.com/manga-zg113826/chapter-191",
      "views": "20",
      "uploaded_time": "Feb 26,20"
    },
    {
      "chapter_name": "Chapter 190",
      "chapter_url": "https://chapmanganelo.com/manga-zg113826/chapter-190",
      "views": "20",
      "uploaded_time": "Feb 26,20"
    },
    {
      "chapter_name": "Chapter 189",
      "chapter_url": "https://chapmanganelo.com/manga-zg113826/chapter-189",
      "views": "19",
      "uploaded_time": "Feb 26,20"
    },
    {
      "chapter_name": "Chapter 188",
      "chapter_url": "https://chapmanganelo.com/manga-zg113826/chapter-188",
      "views": "20",
      "uploaded_time": "Feb 26,20"
    },
    {
      "chapter_name": "Chapter 187",
      "chapter_url": "https://chapmanganelo.com/manga-zg113826/chapter-187",
      "views": "21",
      "uploaded_time": "Feb 26,20"
    },
    {
      "chapter_name": "Chapter 186: So-Ae Tube (4)",
      "chapter_url": "https://chapmanganelo.com/manga-zg113826/chapter-186",
      "views": "26",
      "uploaded_time": "Dec 31,19"
    },
    {
      "chapter_name": "Chapter 185: So-Ae Tube (3)",
      "chapter_url": "https://chapmanganelo.com/manga-zg113826/chapter-185",
      "views": "21",
      "uploaded_time": "Dec 24,19"
    },
    {
      "chapter_name": "Chapter 184: So-Ae Tube (2)",
      "chapter_url": "https://chapmanganelo.com/manga-zg113826/chapter-184",
      "views": "24",
      "uploaded_time": "Dec 18,19"
    },
    {
      "chapter_name": "Chapter 183: So-Ae Tube",
      "chapter_url": "https://chapmanganelo.com/manga-zg113826/chapter-183",
      "views": "22",
      "uploaded_time": "Dec 10,19"
    },
    {
      "chapter_name": "Chapter 182: Days Of Gluttony",
      "chapter_url": "https://chapmanganelo.com/manga-zg113826/chapter-182",
      "views": "23",
      "uploaded_time": "Dec 03,19"
    },
    {
      "chapter_name": "Chapter 181: Woori's Exhibition (2)",
      "chapter_url": "https://chapmanganelo.com/manga-zg113826/chapter-181",
      "views": "24",
      "uploaded_time": "Nov 26,19"
    },
    {
      "chapter_name": "Chapter 180: Woori's Exhibition",
      "chapter_url": "https://chapmanganelo.com/manga-zg113826/chapter-180",
      "views": "24",
      "uploaded_time": "Nov 19,19"
    },
    {
      "chapter_name": "Chapter 179: Who Are You? (2)",
      "chapter_url": "https://chapmanganelo.com/manga-zg113826/chapter-179",
      "views": "25",
      "uploaded_time": "Nov 12,19"
    },
    {
      "chapter_name": "Chapter 178: Who Are You?",
      "chapter_url": "https://chapmanganelo.com/manga-zg113826/chapter-178",
      "views": "26",
      "uploaded_time": "Nov 05,19"
    },
    {
      "chapter_name": "Chapter 177: Visiting Yuna's House (2)",
      "chapter_url": "https://chapmanganelo.com/manga-zg113826/chapter-177",
      "views": "27",
      "uploaded_time": "Oct 29,19"
    },
    {
      "chapter_name": "Chapter 176: Visiting Yuna's House",
      "chapter_url": "https://chapmanganelo.com/manga-zg113826/chapter-176",
      "views": "25",
      "uploaded_time": "Oct 22,19"
    },
    {
      "chapter_name": "Chapter 175: The End And A New Beginning",
      "chapter_url": "https://chapmanganelo.com/manga-zg113826/chapter-175",
      "views": "25",
      "uploaded_time": "Oct 15,19"
    },
    {
      "chapter_name": "Chapter 174: An Old Letter (2)",
      "chapter_url": "https://chapmanganelo.com/manga-zg113826/chapter-174",
      "views": "25",
      "uploaded_time": "Oct 08,19"
    },
    {
      "chapter_name": "Chapter 173: An Old Letter",
      "chapter_url": "https://chapmanganelo.com/manga-zg113826/chapter-173",
      "views": "24",
      "uploaded_time": "Oct 01,19"
    },
    {
      "chapter_name": "Chapter 172: Reunion",
      "chapter_url": "https://chapmanganelo.com/manga-zg113826/chapter-172",
      "views": "25",
      "uploaded_time": "Sep 24,19"
    },
    {
      "chapter_name": "Chapter 171: Middle School (Part 2)",
      "chapter_url": "https://chapmanganelo.com/manga-zg113826/chapter-171",
      "views": "24",
      "uploaded_time": "Sep 17,19"
    },
    {
      "chapter_name": "Chapter 170: Middle School",
      "chapter_url": "https://chapmanganelo.com/manga-zg113826/chapter-170",
      "views": "26",
      "uploaded_time": "Sep 10,19"
    },
    {
      "chapter_name": "Chapter 169: Graduation",
      "chapter_url": "https://chapmanganelo.com/manga-zg113826/chapter-169",
      "views": "24",
      "uploaded_time": "Sep 03,19"
    },
    {
      "chapter_name": "Chapter 168: Falling Apart (Part 6)",
      "chapter_url": "https://chapmanganelo.com/manga-zg113826/chapter-168",
      "views": "23",
      "uploaded_time": "Aug 27,19"
    },
    {
      "chapter_name": "Chapter 167: Falling Apart (Part 5)",
      "chapter_url": "https://chapmanganelo.com/manga-zg113826/chapter-167",
      "views": "24",
      "uploaded_time": "Aug 27,19"
    },
    {
      "chapter_name": "Chapter 166: Falling Apart (Part 4)",
      "chapter_url": "https://chapmanganelo.com/manga-zg113826/chapter-166",
      "views": "24",
      "uploaded_time": "Aug 25,19"
    },
    {
      "chapter_name": "Chapter 165: Falling Apart (Part 3)",
      "chapter_url": "https://chapmanganelo.com/manga-zg113826/chapter-165",
      "views": "23",
      "uploaded_time": "Aug 25,19"
    },
    {
      "chapter_name": "Chapter 164: Falling Apart (Part 2)",
      "chapter_url": "https://chapmanganelo.com/manga-zg113826/chapter-164",
      "views": "24",
      "uploaded_time": "Aug 25,19"
    },
    {
      "chapter_name": "Chapter 163: Falling Apart",
      "chapter_url": "https://chapmanganelo.com/manga-zg113826/chapter-163",
      "views": "24",
      "uploaded_time": "Aug 25,19"
    },
    {
      "chapter_name": "Chapter 162: Yuna (Part 11)",
      "chapter_url": "https://chapmanganelo.com/manga-zg113826/chapter-162",
      "views": "24",
      "uploaded_time": "Aug 25,19"
    },
    {
      "chapter_name": "Chapter 161: That Kid",
      "chapter_url": "https://chapmanganelo.com/manga-zg113826/chapter-161",
      "views": "24",
      "uploaded_time": "Aug 25,19"
    },
    {
      "chapter_name": "Chapter 160: Yuna (Part 10)",
      "chapter_url": "https://chapmanganelo.com/manga-zg113826/chapter-160",
      "views": "24",
      "uploaded_time": "Aug 25,19"
    },
    {
      "chapter_name": "Chapter 159: Yuna (Part 9)",
      "chapter_url": "https://chapmanganelo.com/manga-zg113826/chapter-159",
      "views": "23",
      "uploaded_time": "Aug 25,19"
    },
    {
      "chapter_name": "Chapter 158: Yuna (Part 8)",
      "chapter_url": "https://chapmanganelo.com/manga-zg113826/chapter-158",
      "views": "22",
      "uploaded_time": "Aug 25,19"
    },
    {
      "chapter_name": "Chapter 157: Yuna (Part 7)",
      "chapter_url": "https://chapmanganelo.com/manga-zg113826/chapter-157",
      "views": "27",
      "uploaded_time": "Aug 25,19"
    },
    {
      "chapter_name": "Chapter 156: Yuna (Part 6)",
      "chapter_url": "https://chapmanganelo.com/manga-zg113826/chapter-156",
      "views": "25",
      "uploaded_time": "Aug 25,19"
    },
    {
      "chapter_name": "Chapter 155: Yuna (Part 5)",
      "chapter_url": "https://chapmanganelo.com/manga-zg113826/chapter-155",
      "views": "25",
      "uploaded_time": "Aug 25,19"
    },
    {
      "chapter_name": "Chapter 154: Catkin",
      "chapter_url": "https://chapmanganelo.com/manga-zg113826/chapter-154",
      "views": "24",
      "uploaded_time": "Aug 25,19"
    },
    {
      "chapter_name": "Chapter 153: Yuna (Part 4)",
      "chapter_url": "https://chapmanganelo.com/manga-zg113826/chapter-153",
      "views": "22",
      "uploaded_time": "Aug 25,19"
    },
    {
      "chapter_name": "Chapter 152: Yuna (Part 3)",
      "chapter_url": "https://chapmanganelo.com/manga-zg113826/chapter-152",
      "views": "23",
      "uploaded_time": "Aug 25,19"
    },
    {
      "chapter_name": "Chapter 151: Yuna (Part 2)",
      "chapter_url": "https://chapmanganelo.com/manga-zg113826/chapter-151",
      "views": "29",
      "uploaded_time": "Aug 25,19"
    },
    {
      "chapter_name": "Chapter 150: Yuna (Part 1)",
      "chapter_url": "https://chapmanganelo.com/manga-zg113826/chapter-150",
      "views": "28",
      "uploaded_time": "Aug 25,19"
    },
    {
      "chapter_name": "Chapter 149:  How To Make Up With A Friend (Part 2)",
      "chapter_url": "https://chapmanganelo.com/manga-zg113826/chapter-149",
      "views": "28",
      "uploaded_time": "Aug 25,19"
    },
    {
      "chapter_name": "Chapter 148: How To Make Up With A Friend",
      "chapter_url": "https://chapmanganelo.com/manga-zg113826/chapter-148",
      "views": "32",
      "uploaded_time": "Aug 25,19"
    },
    {
      "chapter_name": "Chapter 147",
      "chapter_url": "https://chapmanganelo.com/manga-zg113826/chapter-147",
      "views": "30",
      "uploaded_time": "Aug 25,19"
    },
    {
      "chapter_name": "Chapter 146: Past Choices",
      "chapter_url": "https://chapmanganelo.com/manga-zg113826/chapter-146",
      "views": "28",
      "uploaded_time": "Aug 25,19"
    },
    {
      "chapter_name": "Chapter 145: Mirae's Birthday (Part 2)",
      "chapter_url": "https://chapmanganelo.com/manga-zg113826/chapter-145",
      "views": "28",
      "uploaded_time": "Aug 25,19"
    },
    {
      "chapter_name": "Chapter 144: Mirae's Birthday",
      "chapter_url": "https://chapmanganelo.com/manga-zg113826/chapter-144",
      "views": "29",
      "uploaded_time": "Aug 25,19"
    },
    {
      "chapter_name": "Chapter 143: Belated Regret",
      "chapter_url": "https://chapmanganelo.com/manga-zg113826/chapter-143",
      "views": "28",
      "uploaded_time": "Aug 25,19"
    },
    {
      "chapter_name": "Chapter 142: Nari And The Avengers (Part 2)",
      "chapter_url": "https://chapmanganelo.com/manga-zg113826/chapter-142",
      "views": "27",
      "uploaded_time": "Aug 25,19"
    },
    {
      "chapter_name": "Chapter 141: Nari And The Avengers",
      "chapter_url": "https://chapmanganelo.com/manga-zg113826/chapter-141",
      "views": "28",
      "uploaded_time": "Aug 25,19"
    },
    {
      "chapter_name": "Chapter 140: Relationship Change (Part 3)",
      "chapter_url": "https://chapmanganelo.com/manga-zg113826/chapter-140",
      "views": "28",
      "uploaded_time": "Aug 25,19"
    },
    {
      "chapter_name": "Chapter 139: Relationship Change (Part 2)",
      "chapter_url": "https://chapmanganelo.com/manga-zg113826/chapter-139",
      "views": "27",
      "uploaded_time": "Aug 25,19"
    },
    {
      "chapter_name": "Chapter 138: Relationship Change",
      "chapter_url": "https://chapmanganelo.com/manga-zg113826/chapter-138",
      "views": "29",
      "uploaded_time": "Aug 25,19"
    },
    {
      "chapter_name": "Chapter 137: The Right Choice (Part5)",
      "chapter_url": "https://chapmanganelo.com/manga-zg113826/chapter-137",
      "views": "24",
      "uploaded_time": "Aug 25,19"
    },
    {
      "chapter_name": "Chapter 136: The Right Choice (Part4)",
      "chapter_url": "https://chapmanganelo.com/manga-zg113826/chapter-136",
      "views": "25",
      "uploaded_time": "Aug 25,19"
    },
    {
      "chapter_name": "Chapter 135: The Right Choice (Part3)",
      "chapter_url": "https://chapmanganelo.com/manga-zg113826/chapter-135",
      "views": "24",
      "uploaded_time": "Aug 25,19"
    },
    {
      "chapter_name": "Chapter 134: The Right Choice (Part2)",
      "chapter_url": "https://chapmanganelo.com/manga-zg113826/chapter-134",
      "views": "27",
      "uploaded_time": "Aug 25,19"
    },
    {
      "chapter_name": "Chapter 133: The Right Choice",
      "chapter_url": "https://chapmanganelo.com/manga-zg113826/chapter-133",
      "views": "26",
      "uploaded_time": "Aug 25,19"
    },
    {
      "chapter_name": "Chapter 132: An Uncomfortable Relationship (Part3)",
      "chapter_url": "https://chapmanganelo.com/manga-zg113826/chapter-132",
      "views": "25",
      "uploaded_time": "Aug 25,19"
    },
    {
      "chapter_name": "Chapter 131: An Uncomfortable Relationship (Part2)",
      "chapter_url": "https://chapmanganelo.com/manga-zg113826/chapter-131",
      "views": "24",
      "uploaded_time": "Aug 25,19"
    },
    {
      "chapter_name": "Chapter 130: An Uncomfortable Relationship",
      "chapter_url": "https://chapmanganelo.com/manga-zg113826/chapter-130",
      "views": "28",
      "uploaded_time": "Aug 25,19"
    },
    {
      "chapter_name": "Chapter 129: End Of A Friendship",
      "chapter_url": "https://chapmanganelo.com/manga-zg113826/chapter-129",
      "views": "27",
      "uploaded_time": "Aug 25,19"
    },
    {
      "chapter_name": "Chapter 128: Vacation Ceremony",
      "chapter_url": "https://chapmanganelo.com/manga-zg113826/chapter-128",
      "views": "25",
      "uploaded_time": "Aug 25,19"
    },
    {
      "chapter_name": "Chapter 127: A Strange Love Triangle (Part 3)",
      "chapter_url": "https://chapmanganelo.com/manga-zg113826/chapter-127",
      "views": "27",
      "uploaded_time": "Aug 25,19"
    },
    {
      "chapter_name": "Chapter 126",
      "chapter_url": "https://chapmanganelo.com/manga-zg113826/chapter-126",
      "views": "26",
      "uploaded_time": "Aug 25,19"
    },
    {
      "chapter_name": "Chapter 125",
      "chapter_url": "https://chapmanganelo.com/manga-zg113826/chapter-125",
      "views": "26",
      "uploaded_time": "Aug 25,19"
    },
    {
      "chapter_name": "Chapter 124",
      "chapter_url": "https://chapmanganelo.com/manga-zg113826/chapter-124",
      "views": "27",
      "uploaded_time": "Aug 25,19"
    },
    {
      "chapter_name": "Chapter 123: How To Make Compliments (Part 2)",
      "chapter_url": "https://chapmanganelo.com/manga-zg113826/chapter-123",
      "views": "28",
      "uploaded_time": "Aug 25,19"
    },
    {
      "chapter_name": "Chapter 122: How To Make Compliments (Part 1)",
      "chapter_url": "https://chapmanganelo.com/manga-zg113826/chapter-122",
      "views": "26",
      "uploaded_time": "Aug 25,19"
    },
    {
      "chapter_name": "Chapter 121: Meeting Him In Person",
      "chapter_url": "https://chapmanganelo.com/manga-zg113826/chapter-121",
      "views": "26",
      "uploaded_time": "Aug 25,19"
    },
    {
      "chapter_name": "Chapter 120: Conclusion",
      "chapter_url": "https://chapmanganelo.com/manga-zg113826/chapter-120",
      "views": "26",
      "uploaded_time": "Aug 25,19"
    },
    {
      "chapter_name": "Chapter 119: Counterattack",
      "chapter_url": "https://chapmanganelo.com/manga-zg113826/chapter-119",
      "views": "25",
      "uploaded_time": "Aug 25,19"
    },
    {
      "chapter_name": "Chapter 118: High School Animal Farm (Part 2)",
      "chapter_url": "https://chapmanganelo.com/manga-zg113826/chapter-118",
      "views": "27",
      "uploaded_time": "Aug 25,19"
    },
    {
      "chapter_name": "Chapter 117: High School Animal Farm (Part 1)",
      "chapter_url": "https://chapmanganelo.com/manga-zg113826/chapter-117",
      "views": "25",
      "uploaded_time": "Aug 25,19"
    },
    {
      "chapter_name": "Chapter 116",
      "chapter_url": "https://chapmanganelo.com/manga-zg113826/chapter-116",
      "views": "28",
      "uploaded_time": "Aug 25,19"
    },
    {
      "chapter_name": "Chapter 115",
      "chapter_url": "https://chapmanganelo.com/manga-zg113826/chapter-115",
      "views": "27",
      "uploaded_time": "Aug 25,19"
    },
    {
      "chapter_name": "Chapter 114: Final Exam (Part 2)",
      "chapter_url": "https://chapmanganelo.com/manga-zg113826/chapter-114",
      "views": "28",
      "uploaded_time": "Aug 25,19"
    },
    {
      "chapter_name": "Chapter 113: Final Exam (Part 1)",
      "chapter_url": "https://chapmanganelo.com/manga-zg113826/chapter-113",
      "views": "28",
      "uploaded_time": "Aug 25,19"
    },
    {
      "chapter_name": "Chapter 112: Mirae (Part 14)",
      "chapter_url": "https://chapmanganelo.com/manga-zg113826/chapter-112",
      "views": "26",
      "uploaded_time": "Aug 25,19"
    },
    {
      "chapter_name": "Chapter 111",
      "chapter_url": "https://chapmanganelo.com/manga-zg113826/chapter-111",
      "views": "27",
      "uploaded_time": "Aug 25,19"
    },
    {
      "chapter_name": "Chapter 110: Mirae (Part 12)",
      "chapter_url": "https://chapmanganelo.com/manga-zg113826/chapter-110",
      "views": "26",
      "uploaded_time": "Aug 25,19"
    },
    {
      "chapter_name": "Chapter 109: Mirae (Part 11)",
      "chapter_url": "https://chapmanganelo.com/manga-zg113826/chapter-109",
      "views": "23",
      "uploaded_time": "Aug 25,19"
    },
    {
      "chapter_name": "Chapter 108",
      "chapter_url": "https://chapmanganelo.com/manga-zg113826/chapter-108",
      "views": "27",
      "uploaded_time": "Aug 25,19"
    },
    {
      "chapter_name": "Chapter 107",
      "chapter_url": "https://chapmanganelo.com/manga-zg113826/chapter-107",
      "views": "24",
      "uploaded_time": "Aug 25,19"
    },
    {
      "chapter_name": "Chapter 106: Mirae (Part 8)",
      "chapter_url": "https://chapmanganelo.com/manga-zg113826/chapter-106",
      "views": "25",
      "uploaded_time": "Aug 25,19"
    },
    {
      "chapter_name": "Chapter 105",
      "chapter_url": "https://chapmanganelo.com/manga-zg113826/chapter-105",
      "views": "26",
      "uploaded_time": "Aug 25,19"
    },
    {
      "chapter_name": "Chapter 104",
      "chapter_url": "https://chapmanganelo.com/manga-zg113826/chapter-104",
      "views": "23",
      "uploaded_time": "Aug 25,19"
    },
    {
      "chapter_name": "Chapter 103",
      "chapter_url": "https://chapmanganelo.com/manga-zg113826/chapter-103",
      "views": "25",
      "uploaded_time": "Aug 25,19"
    },
    {
      "chapter_name": "Chapter 102: Mirae (Part 4)",
      "chapter_url": "https://chapmanganelo.com/manga-zg113826/chapter-102",
      "views": "28",
      "uploaded_time": "Aug 25,19"
    },
    {
      "chapter_name": "Chapter 101: Mirae (Part 3)",
      "chapter_url": "https://chapmanganelo.com/manga-zg113826/chapter-101",
      "views": "24",
      "uploaded_time": "Aug 25,19"
    },
    {
      "chapter_name": "Chapter 100: Mirae (Part 2)",
      "chapter_url": "https://chapmanganelo.com/manga-zg113826/chapter-100",
      "views": "25",
      "uploaded_time": "Aug 25,19"
    },
    {
      "chapter_name": "Chapter 99: Mirae (Part 1)",
      "chapter_url": "https://chapmanganelo.com/manga-zg113826/chapter-99",
      "views": "26",
      "uploaded_time": "Aug 25,19"
    },
    {
      "chapter_name": "Chapter 98: The Secret (3)",
      "chapter_url": "https://chapmanganelo.com/manga-zg113826/chapter-98",
      "views": "28",
      "uploaded_time": "Aug 25,19"
    },
    {
      "chapter_name": "Chapter 97: The Secret (2)",
      "chapter_url": "https://chapmanganelo.com/manga-zg113826/chapter-97",
      "views": "26",
      "uploaded_time": "Aug 25,19"
    },
    {
      "chapter_name": "Chapter 96: The Secret",
      "chapter_url": "https://chapmanganelo.com/manga-zg113826/chapter-96",
      "views": "27",
      "uploaded_time": "Aug 25,19"
    },
    {
      "chapter_name": "Chapter 95",
      "chapter_url": "https://chapmanganelo.com/manga-zg113826/chapter-95",
      "views": "29",
      "uploaded_time": "Aug 25,19"
    },
    {
      "chapter_name": "Chapter 94",
      "chapter_url": "https://chapmanganelo.com/manga-zg113826/chapter-94",
      "views": "26",
      "uploaded_time": "Aug 25,19"
    },
    {
      "chapter_name": "Chapter 93",
      "chapter_url": "https://chapmanganelo.com/manga-zg113826/chapter-93",
      "views": "27",
      "uploaded_time": "Aug 25,19"
    },
    {
      "chapter_name": "Chapter 92",
      "chapter_url": "https://chapmanganelo.com/manga-zg113826/chapter-92",
      "views": "27",
      "uploaded_time": "Aug 25,19"
    },
    {
      "chapter_name": "Chapter 91: Superficial Relationships (1)",
      "chapter_url": "https://chapmanganelo.com/manga-zg113826/chapter-91",
      "views": "31",
      "uploaded_time": "Aug 25,19"
    },
    {
      "chapter_name": "Chapter 90 : The Two Sides Of Love (Part 3)",
      "chapter_url": "https://chapmanganelo.com/manga-zg113826/chapter-90",
      "views": "29",
      "uploaded_time": "Aug 25,19"
    },
    {
      "chapter_name": "Chapter 89",
      "chapter_url": "https://chapmanganelo.com/manga-zg113826/chapter-89",
      "views": "30",
      "uploaded_time": "Aug 25,19"
    },
    {
      "chapter_name": "Chapter 88",
      "chapter_url": "https://chapmanganelo.com/manga-zg113826/chapter-88",
      "views": "28",
      "uploaded_time": "Aug 25,19"
    },
    {
      "chapter_name": "Chapter 87 : The Cafeteria Guy (Part 3)",
      "chapter_url": "https://chapmanganelo.com/manga-zg113826/chapter-87",
      "views": "29",
      "uploaded_time": "Aug 25,19"
    },
    {
      "chapter_name": "Chapter 86",
      "chapter_url": "https://chapmanganelo.com/manga-zg113826/chapter-86",
      "views": "29",
      "uploaded_time": "Aug 25,19"
    },
    {
      "chapter_name": "Chapter 85: The Cafeteria Guy",
      "chapter_url": "https://chapmanganelo.com/manga-zg113826/chapter-85",
      "views": "27",
      "uploaded_time": "Aug 25,19"
    },
    {
      "chapter_name": "Chapter 84",
      "chapter_url": "https://chapmanganelo.com/manga-zg113826/chapter-84",
      "views": "29",
      "uploaded_time": "Aug 25,19"
    },
    {
      "chapter_name": "Chapter 83",
      "chapter_url": "https://chapmanganelo.com/manga-zg113826/chapter-83",
      "views": "29",
      "uploaded_time": "Aug 25,19"
    },
    {
      "chapter_name": "Chapter 82: Bygones",
      "chapter_url": "https://chapmanganelo.com/manga-zg113826/chapter-82",
      "views": "25",
      "uploaded_time": "Aug 25,19"
    },
    {
      "chapter_name": "Chapter 81",
      "chapter_url": "https://chapmanganelo.com/manga-zg113826/chapter-81",
      "views": "29",
      "uploaded_time": "Aug 25,19"
    },
    {
      "chapter_name": "Chapter 80: Friends (Part 1)",
      "chapter_url": "https://chapmanganelo.com/manga-zg113826/chapter-80",
      "views": "26",
      "uploaded_time": "Aug 25,19"
    },
    {
      "chapter_name": "Chapter 79",
      "chapter_url": "https://chapmanganelo.com/manga-zg113826/chapter-79",
      "views": "29",
      "uploaded_time": "Aug 25,19"
    },
    {
      "chapter_name": "Chapter 78",
      "chapter_url": "https://chapmanganelo.com/manga-zg113826/chapter-78",
      "views": "26",
      "uploaded_time": "Aug 25,19"
    },
    {
      "chapter_name": "Chapter 77",
      "chapter_url": "https://chapmanganelo.com/manga-zg113826/chapter-77",
      "views": "28",
      "uploaded_time": "Aug 25,19"
    },
    {
      "chapter_name": "Chapter 76",
      "chapter_url": "https://chapmanganelo.com/manga-zg113826/chapter-76",
      "views": "28",
      "uploaded_time": "Aug 25,19"
    },
    {
      "chapter_name": "Chapter 75",
      "chapter_url": "https://chapmanganelo.com/manga-zg113826/chapter-75",
      "views": "28",
      "uploaded_time": "Aug 25,19"
    },
    {
      "chapter_name": "Chapter 74: Seonji (Part 10)",
      "chapter_url": "https://chapmanganelo.com/manga-zg113826/chapter-74",
      "views": "26",
      "uploaded_time": "Aug 25,19"
    },
    {
      "chapter_name": "Chapter 73",
      "chapter_url": "https://chapmanganelo.com/manga-zg113826/chapter-73",
      "views": "28",
      "uploaded_time": "Aug 25,19"
    },
    {
      "chapter_name": "Chapter 72",
      "chapter_url": "https://chapmanganelo.com/manga-zg113826/chapter-72",
      "views": "27",
      "uploaded_time": "Aug 25,19"
    },
    {
      "chapter_name": "Chapter 71",
      "chapter_url": "https://chapmanganelo.com/manga-zg113826/chapter-71",
      "views": "26",
      "uploaded_time": "Aug 25,19"
    },
    {
      "chapter_name": "Chapter 70",
      "chapter_url": "https://chapmanganelo.com/manga-zg113826/chapter-70",
      "views": "28",
      "uploaded_time": "Aug 25,19"
    },
    {
      "chapter_name": "Chapter 69",
      "chapter_url": "https://chapmanganelo.com/manga-zg113826/chapter-69",
      "views": "29",
      "uploaded_time": "Aug 25,19"
    },
    {
      "chapter_name": "Chapter 68",
      "chapter_url": "https://chapmanganelo.com/manga-zg113826/chapter-68",
      "views": "29",
      "uploaded_time": "Aug 25,19"
    },
    {
      "chapter_name": "Chapter 67",
      "chapter_url": "https://chapmanganelo.com/manga-zg113826/chapter-67",
      "views": "28",
      "uploaded_time": "Aug 25,19"
    },
    {
      "chapter_name": "Chapter 66",
      "chapter_url": "https://chapmanganelo.com/manga-zg113826/chapter-66",
      "views": "29",
      "uploaded_time": "Aug 25,19"
    },
    {
      "chapter_name": "Chapter 65",
      "chapter_url": "https://chapmanganelo.com/manga-zg113826/chapter-65",
      "views": "30",
      "uploaded_time": "Aug 25,19"
    },
    {
      "chapter_name": "Chapter 64",
      "chapter_url": "https://chapmanganelo.com/manga-zg113826/chapter-64",
      "views": "30",
      "uploaded_time": "Aug 25,19"
    },
    {
      "chapter_name": "Chapter 63",
      "chapter_url": "https://chapmanganelo.com/manga-zg113826/chapter-63",
      "views": "31",
      "uploaded_time": "Aug 25,19"
    },
    {
      "chapter_name": "Chapter 62",
      "chapter_url": "https://chapmanganelo.com/manga-zg113826/chapter-62",
      "views": "30",
      "uploaded_time": "Aug 25,19"
    },
    {
      "chapter_name": "Chapter 61",
      "chapter_url": "https://chapmanganelo.com/manga-zg113826/chapter-61",
      "views": "29",
      "uploaded_time": "Aug 25,19"
    },
    {
      "chapter_name": "Chapter 60",
      "chapter_url": "https://chapmanganelo.com/manga-zg113826/chapter-60",
      "views": "32",
      "uploaded_time": "Aug 25,19"
    },
    {
      "chapter_name": "Chapter 59",
      "chapter_url": "https://chapmanganelo.com/manga-zg113826/chapter-59",
      "views": "29",
      "uploaded_time": "Aug 25,19"
    },
    {
      "chapter_name": "Chapter 58",
      "chapter_url": "https://chapmanganelo.com/manga-zg113826/chapter-58",
      "views": "31",
      "uploaded_time": "Aug 25,19"
    },
    {
      "chapter_name": "Chapter 57 : The Perm",
      "chapter_url": "https://chapmanganelo.com/manga-zg113826/chapter-57",
      "views": "32",
      "uploaded_time": "Aug 25,19"
    },
    {
      "chapter_name": "Chapter 56 : The Reunion (Part 7)",
      "chapter_url": "https://chapmanganelo.com/manga-zg113826/chapter-56",
      "views": "32",
      "uploaded_time": "Aug 25,19"
    },
    {
      "chapter_name": "Chapter 55",
      "chapter_url": "https://chapmanganelo.com/manga-zg113826/chapter-55",
      "views": "30",
      "uploaded_time": "Aug 25,19"
    },
    {
      "chapter_name": "Chapter 54",
      "chapter_url": "https://chapmanganelo.com/manga-zg113826/chapter-54",
      "views": "27",
      "uploaded_time": "Aug 25,19"
    },
    {
      "chapter_name": "Chapter 53",
      "chapter_url": "https://chapmanganelo.com/manga-zg113826/chapter-53",
      "views": "28",
      "uploaded_time": "Aug 25,19"
    },
    {
      "chapter_name": "Chapter 52",
      "chapter_url": "https://chapmanganelo.com/manga-zg113826/chapter-52",
      "views": "31",
      "uploaded_time": "Aug 25,19"
    },
    {
      "chapter_name": "Chapter 51",
      "chapter_url": "https://chapmanganelo.com/manga-zg113826/chapter-51",
      "views": "30",
      "uploaded_time": "Aug 25,19"
    },
    {
      "chapter_name": "Chapter 50",
      "chapter_url": "https://chapmanganelo.com/manga-zg113826/chapter-50",
      "views": "31",
      "uploaded_time": "Aug 25,19"
    },
    {
      "chapter_name": "Chapter 49",
      "chapter_url": "https://chapmanganelo.com/manga-zg113826/chapter-49",
      "views": "31",
      "uploaded_time": "Aug 25,19"
    },
    {
      "chapter_name": "Chapter 48",
      "chapter_url": "https://chapmanganelo.com/manga-zg113826/chapter-48",
      "views": "29",
      "uploaded_time": "Aug 25,19"
    },
    {
      "chapter_name": "Chapter 47 : The Lives Of Others (Part2)",
      "chapter_url": "https://chapmanganelo.com/manga-zg113826/chapter-47",
      "views": "32",
      "uploaded_time": "Aug 25,19"
    },
    {
      "chapter_name": "Chapter 46",
      "chapter_url": "https://chapmanganelo.com/manga-zg113826/chapter-46",
      "views": "32",
      "uploaded_time": "Aug 25,19"
    },
    {
      "chapter_name": "Chapter 45 : Shes-Just-Shy-Part3",
      "chapter_url": "https://chapmanganelo.com/manga-zg113826/chapter-45",
      "views": "31",
      "uploaded_time": "Aug 25,19"
    },
    {
      "chapter_name": "Chapter 44: She's Just Shy (Part 2)",
      "chapter_url": "https://chapmanganelo.com/manga-zg113826/chapter-44",
      "views": "27",
      "uploaded_time": "Aug 25,19"
    },
    {
      "chapter_name": "Chapter 43 : She's Just Shy (Part1)",
      "chapter_url": "https://chapmanganelo.com/manga-zg113826/chapter-43",
      "views": "32",
      "uploaded_time": "Aug 25,19"
    },
    {
      "chapter_name": "Chapter 42: What Goes Around Comes Around (Part 2)",
      "chapter_url": "https://chapmanganelo.com/manga-zg113826/chapter-42",
      "views": "31",
      "uploaded_time": "Aug 25,19"
    },
    {
      "chapter_name": "Chapter 41: What Goes Around Comes Around (Part 1)",
      "chapter_url": "https://chapmanganelo.com/manga-zg113826/chapter-41",
      "views": "28",
      "uploaded_time": "Aug 25,19"
    },
    {
      "chapter_name": "Chapter 40: The And",
      "chapter_url": "https://chapmanganelo.com/manga-zg113826/chapter-40",
      "views": "33",
      "uploaded_time": "Aug 25,19"
    },
    {
      "chapter_name": "Chapter 39 : The End",
      "chapter_url": "https://chapmanganelo.com/manga-zg113826/chapter-39",
      "views": "32",
      "uploaded_time": "Aug 25,19"
    },
    {
      "chapter_name": "Chapter 38 : After-The-Storm",
      "chapter_url": "https://chapmanganelo.com/manga-zg113826/chapter-38",
      "views": "29",
      "uploaded_time": "Aug 25,19"
    },
    {
      "chapter_name": "Chapter 37: Reunion",
      "chapter_url": "https://chapmanganelo.com/manga-zg113826/chapter-37",
      "views": "31",
      "uploaded_time": "Aug 25,19"
    },
    {
      "chapter_name": "Chapter 36",
      "chapter_url": "https://chapmanganelo.com/manga-zg113826/chapter-36",
      "views": "30",
      "uploaded_time": "Aug 25,19"
    },
    {
      "chapter_name": "Chapter 35: Realizaton",
      "chapter_url": "https://chapmanganelo.com/manga-zg113826/chapter-35",
      "views": "29",
      "uploaded_time": "Aug 25,19"
    },
    {
      "chapter_name": "Chapter 34",
      "chapter_url": "https://chapmanganelo.com/manga-zg113826/chapter-34",
      "views": "33",
      "uploaded_time": "Aug 25,19"
    },
    {
      "chapter_name": "Chapter 33",
      "chapter_url": "https://chapmanganelo.com/manga-zg113826/chapter-33",
      "views": "29",
      "uploaded_time": "Aug 25,19"
    },
    {
      "chapter_name": "Chapter 32",
      "chapter_url": "https://chapmanganelo.com/manga-zg113826/chapter-32",
      "views": "31",
      "uploaded_time": "Aug 25,19"
    },
    {
      "chapter_name": "Chapter 31: Side Story 1: The Gift",
      "chapter_url": "https://chapmanganelo.com/manga-zg113826/chapter-31",
      "views": "29",
      "uploaded_time": "Aug 25,19"
    },
    {
      "chapter_name": "Chapter 30: The Duck And The Swans",
      "chapter_url": "https://chapmanganelo.com/manga-zg113826/chapter-30",
      "views": "31",
      "uploaded_time": "Aug 25,19"
    },
    {
      "chapter_name": "Chapter 29",
      "chapter_url": "https://chapmanganelo.com/manga-zg113826/chapter-29",
      "views": "31",
      "uploaded_time": "Aug 25,19"
    },
    {
      "chapter_name": "Chapter 28",
      "chapter_url": "https://chapmanganelo.com/manga-zg113826/chapter-28",
      "views": "31",
      "uploaded_time": "Aug 25,19"
    },
    {
      "chapter_name": "Chapter 27",
      "chapter_url": "https://chapmanganelo.com/manga-zg113826/chapter-27",
      "views": "30",
      "uploaded_time": "Aug 25,19"
    },
    {
      "chapter_name": "Chapter 26",
      "chapter_url": "https://chapmanganelo.com/manga-zg113826/chapter-26",
      "views": "29",
      "uploaded_time": "Aug 25,19"
    },
    {
      "chapter_name": "Chapter 25",
      "chapter_url": "https://chapmanganelo.com/manga-zg113826/chapter-25",
      "views": "32",
      "uploaded_time": "Aug 25,19"
    },
    {
      "chapter_name": "Chapter 24",
      "chapter_url": "https://chapmanganelo.com/manga-zg113826/chapter-24",
      "views": "33",
      "uploaded_time": "Aug 25,19"
    },
    {
      "chapter_name": "Chapter 23: The Food Chain (Part1)",
      "chapter_url": "https://chapmanganelo.com/manga-zg113826/chapter-23",
      "views": "31",
      "uploaded_time": "Aug 25,19"
    },
    {
      "chapter_name": "Chapter 22",
      "chapter_url": "https://chapmanganelo.com/manga-zg113826/chapter-22",
      "views": "33",
      "uploaded_time": "Aug 25,19"
    },
    {
      "chapter_name": "Chapter 21",
      "chapter_url": "https://chapmanganelo.com/manga-zg113826/chapter-21",
      "views": "33",
      "uploaded_time": "Aug 25,19"
    },
    {
      "chapter_name": "Chapter 20",
      "chapter_url": "https://chapmanganelo.com/manga-zg113826/chapter-20",
      "views": "31",
      "uploaded_time": "Aug 25,19"
    },
    {
      "chapter_name": "Chapter 19",
      "chapter_url": "https://chapmanganelo.com/manga-zg113826/chapter-19",
      "views": "34",
      "uploaded_time": "Aug 25,19"
    },
    {
      "chapter_name": "Chapter 18 : Transformation (Part2)",
      "chapter_url": "https://chapmanganelo.com/manga-zg113826/chapter-18",
      "views": "34",
      "uploaded_time": "Aug 25,19"
    },
    {
      "chapter_name": "Chapter 17 : Transformation (Part1)",
      "chapter_url": "https://chapmanganelo.com/manga-zg113826/chapter-17",
      "views": "33",
      "uploaded_time": "Aug 25,19"
    },
    {
      "chapter_name": "Chapter 16: An Ominous Foreboding",
      "chapter_url": "https://chapmanganelo.com/manga-zg113826/chapter-16",
      "views": "35",
      "uploaded_time": "Aug 25,19"
    },
    {
      "chapter_name": "Chapter 15",
      "chapter_url": "https://chapmanganelo.com/manga-zg113826/chapter-15",
      "views": "34",
      "uploaded_time": "Aug 25,19"
    },
    {
      "chapter_name": "Chapter 14 : Group Activity (1)",
      "chapter_url": "https://chapmanganelo.com/manga-zg113826/chapter-14",
      "views": "33",
      "uploaded_time": "Aug 25,19"
    },
    {
      "chapter_name": "Chapter 13 : Got Prettier",
      "chapter_url": "https://chapmanganelo.com/manga-zg113826/chapter-13",
      "views": "32",
      "uploaded_time": "Aug 25,19"
    },
    {
      "chapter_name": "Chapter 12 : Heart Flutters",
      "chapter_url": "https://chapmanganelo.com/manga-zg113826/chapter-12",
      "views": "34",
      "uploaded_time": "Aug 25,19"
    },
    {
      "chapter_name": "Chapter 11 : Gloomy Day",
      "chapter_url": "https://chapmanganelo.com/manga-zg113826/chapter-11",
      "views": "33",
      "uploaded_time": "Aug 25,19"
    },
    {
      "chapter_name": "Chapter 10 : Getting To Know A Person By Spending Time With Them",
      "chapter_url": "https://chapmanganelo.com/manga-zg113826/chapter-10",
      "views": "35",
      "uploaded_time": "Aug 25,19"
    },
    {
      "chapter_name": "Chapter 9 : I Need Some Determination (2)",
      "chapter_url": "https://chapmanganelo.com/manga-zg113826/chapter-9",
      "views": "36",
      "uploaded_time": "Aug 25,19"
    },
    {
      "chapter_name": "Chapter 8 : I Need Some Determination (1)",
      "chapter_url": "https://chapmanganelo.com/manga-zg113826/chapter-8",
      "views": "37",
      "uploaded_time": "Aug 25,19"
    },
    {
      "chapter_name": "Chapter 7 : Turtle Candy For White Day (002)",
      "chapter_url": "https://chapmanganelo.com/manga-zg113826/chapter-7",
      "views": "39",
      "uploaded_time": "Aug 25,19"
    },
    {
      "chapter_name": "Chapter 6 : Turtle Candy For White Day (1)",
      "chapter_url": "https://chapmanganelo.com/manga-zg113826/chapter-6",
      "views": "42",
      "uploaded_time": "Aug 25,19"
    },
    {
      "chapter_name": "Chapter 5",
      "chapter_url": "https://chapmanganelo.com/manga-zg113826/chapter-5",
      "views": "27",
      "uploaded_time": "Jul 25,20"
    },
    {
      "chapter_name": "Chapter 4 : Don't Look At Me With That Expression (2)",
      "chapter_url": "https://chapmanganelo.com/manga-zg113826/chapter-4",
      "views": "44",
      "uploaded_time": "Aug 25,19"
    },
    {
      "chapter_name": "Chapter 3 : Don't Look At Me With That Expression (1)",
      "chapter_url": "https://chapmanganelo.com/manga-zg113826/chapter-3",
      "views": "50",
      "uploaded_time": "Aug 25,19"
    },
    {
      "chapter_name": "Chapter 2 : The Duck And The Swans",
      "chapter_url": "https://chapmanganelo.com/manga-zg113826/chapter-2",
      "views": "57",
      "uploaded_time": "Aug 25,19"
    },
    {
      "chapter_name": "Chapter 1 : Opening Ceremony",
      "chapter_url": "https://chapmanganelo.com/manga-zg113826/chapter-1",
      "views": "95",
      "uploaded_time": "Aug 25,19"
    }
  ]
}