{
  "title": "King Of Thorn",
  "img": "https://avt.mkklcdnv6temp.com/fld/100/f/6-1732783144-nw.webp",
  "alternative_title": "\u3044\u3070\u3089\u306e\u738b ; \u53e4\u57ce\u8346\u68d8\u738b ; \u53e4\u57ce\u834a\u68d8\u738b ; Ibara no Oh ; Ibara no Ou ; K\u00f6nig der Dornen ; King of Thorns",
  "authors": [],
  "status": "\u3044\u3070\u3089\u306e\u738b ; \u53e4\u57ce\u8346\u68d8\u738b ; \u53e4\u57ce\u834a\u68d8\u738b ; Ibara no Oh ; Ibara no Ou ; K\u00f6nig der Dornen ; King of Thorns",
  "genres": [
    "Iwahara Yuji",
    "Action",
    "Horror",
    "Mystery",
    "Psychological",
    "Sci fi",
    "Seinen",
    "Tragedy"
  ],
  "updated_time": "Jan 20,2016 - 13:26 PM",
  "description": "Description :\r\n        Two twins, separated by fatal illness and a selective cure. Kasumi and her sister, Shizuku, were infected with the Medusa virus, which slowly turns the victim to stone. There is no cure, but of the two only Kasumi is selected to go into a sort of cryogenically frozen state along with 159 others until a cure is found. At some point in the undetermined future, Kasumi awakens to find herself and others who were in suspended animation in an unfamiliar world with violent monsters. Resolving to unlock the mysteries of her current situation and the fate of her twin sister, Kasumi struggles to survive in a treacherous world.",
  "chapters": [
    {
      "chapter_name": "Vol.6 Chapter 37 : Beyond Thought",
      "chapter_url": "https://chapmanganelo.com/manga-sg106726/chapter-37",
      "views": "42",
      "uploaded_time": "Aug 25,19"
    },
    {
      "chapter_name": "Vol.6 Chapter 36 : Deep Trench",
      "chapter_url": "https://chapmanganelo.com/manga-sg106726/chapter-36",
      "views": "28",
      "uploaded_time": "Aug 25,19"
    },
    {
      "chapter_name": "Vol.6 Chapter 35 : The Last Battle",
      "chapter_url": "https://chapmanganelo.com/manga-sg106726/chapter-35",
      "views": "26",
      "uploaded_time": "Aug 25,19"
    },
    {
      "chapter_name": "Vol.6 Chapter 34 : Marco's Resurrection",
      "chapter_url": "https://chapmanganelo.com/manga-sg106726/chapter-34",
      "views": "28",
      "uploaded_time": "Aug 25,19"
    },
    {
      "chapter_name": "Vol.6 Chapter 33 : Encounter",
      "chapter_url": "https://chapmanganelo.com/manga-sg106726/chapter-33",
      "views": "28",
      "uploaded_time": "Aug 25,19"
    },
    {
      "chapter_name": "Vol.6 Chapter 32 : Marco's Death",
      "chapter_url": "https://chapmanganelo.com/manga-sg106726/chapter-32",
      "views": "27",
      "uploaded_time": "Aug 25,19"
    },
    {
      "chapter_name": "Vol.5 Chapter 31 : The Elite",
      "chapter_url": "https://chapmanganelo.com/manga-sg106726/chapter-31",
      "views": "27",
      "uploaded_time": "Aug 25,19"
    },
    {
      "chapter_name": "Vol.5 Chapter 30 : An Entity Named Shizuku",
      "chapter_url": "https://chapmanganelo.com/manga-sg106726/chapter-30",
      "views": "25",
      "uploaded_time": "Aug 25,19"
    },
    {
      "chapter_name": "Vol.5 Chapter 29 : Flaws And Reality",
      "chapter_url": "https://chapmanganelo.com/manga-sg106726/chapter-29",
      "views": "25",
      "uploaded_time": "Aug 25,19"
    },
    {
      "chapter_name": "Vol.5 Chapter 28 : Alice's World",
      "chapter_url": "https://chapmanganelo.com/manga-sg106726/chapter-28",
      "views": "26",
      "uploaded_time": "Aug 25,19"
    },
    {
      "chapter_name": "Vol.5 Chapter 27 : A Reunion With The Archenemy",
      "chapter_url": "https://chapmanganelo.com/manga-sg106726/chapter-27",
      "views": "26",
      "uploaded_time": "Aug 25,19"
    },
    {
      "chapter_name": "Vol.5 Chapter 26 : A Fragment Of The Heart",
      "chapter_url": "https://chapmanganelo.com/manga-sg106726/chapter-26",
      "views": "28",
      "uploaded_time": "Aug 25,19"
    },
    {
      "chapter_name": "Vol.5 Chapter 25 : The Death Of Kathryn",
      "chapter_url": "https://chapmanganelo.com/manga-sg106726/chapter-25",
      "views": "27",
      "uploaded_time": "Aug 25,19"
    },
    {
      "chapter_name": "Vol.4 Chapter 24 : Wounds",
      "chapter_url": "https://chapmanganelo.com/manga-sg106726/chapter-24",
      "views": "26",
      "uploaded_time": "Aug 25,19"
    },
    {
      "chapter_name": "Vol.4 Chapter 23 : The Bird In The Cage...  Part 3",
      "chapter_url": "https://chapmanganelo.com/manga-sg106726/chapter-23",
      "views": "26",
      "uploaded_time": "Aug 25,19"
    },
    {
      "chapter_name": "Vol.4 Chapter 22 : The Bird In The Cage...  Part 2",
      "chapter_url": "https://chapmanganelo.com/manga-sg106726/chapter-22",
      "views": "26",
      "uploaded_time": "Aug 25,19"
    },
    {
      "chapter_name": "Vol.4 Chapter 21 : The Bird In The Cage...  Part 1",
      "chapter_url": "https://chapmanganelo.com/manga-sg106726/chapter-21",
      "views": "28",
      "uploaded_time": "Aug 25,19"
    },
    {
      "chapter_name": "Vol.4 Chapter 20 : Marco's Enemy",
      "chapter_url": "https://chapmanganelo.com/manga-sg106726/chapter-20",
      "views": "27",
      "uploaded_time": "Aug 25,19"
    },
    {
      "chapter_name": "Vol.4 Chapter 19 : Freefall",
      "chapter_url": "https://chapmanganelo.com/manga-sg106726/chapter-19",
      "views": "27",
      "uploaded_time": "Aug 25,19"
    },
    {
      "chapter_name": "Vol.4 Chapter 18 : The Truth About Medusa",
      "chapter_url": "https://chapmanganelo.com/manga-sg106726/chapter-18",
      "views": "28",
      "uploaded_time": "Aug 25,19"
    },
    {
      "chapter_name": "Vol.3 Chapter 17 : The Rules Of Trust",
      "chapter_url": "https://chapmanganelo.com/manga-sg106726/chapter-17",
      "views": "28",
      "uploaded_time": "Aug 25,19"
    },
    {
      "chapter_name": "Vol.3 Chapter 16 : The Water's Secret",
      "chapter_url": "https://chapmanganelo.com/manga-sg106726/chapter-16",
      "views": "27",
      "uploaded_time": "Aug 25,19"
    },
    {
      "chapter_name": "Vol.3 Chapter 15 : What Really Happened That Day",
      "chapter_url": "https://chapmanganelo.com/manga-sg106726/chapter-15",
      "views": "27",
      "uploaded_time": "Aug 25,19"
    },
    {
      "chapter_name": "Vol.3 Chapter 14 : A Dangerous Place",
      "chapter_url": "https://chapmanganelo.com/manga-sg106726/chapter-14",
      "views": "30",
      "uploaded_time": "Aug 25,19"
    },
    {
      "chapter_name": "Vol.3 Chapter 13 : A Deep Place",
      "chapter_url": "https://chapmanganelo.com/manga-sg106726/chapter-13",
      "views": "29",
      "uploaded_time": "Aug 25,19"
    },
    {
      "chapter_name": "Vol.3 Chapter 12 : The End Of The World",
      "chapter_url": "https://chapmanganelo.com/manga-sg106726/chapter-12",
      "views": "31",
      "uploaded_time": "Aug 25,19"
    },
    {
      "chapter_name": "Vol.2 Chapter 11 : The Cross And The Crown Of Thorns",
      "chapter_url": "https://chapmanganelo.com/manga-sg106726/chapter-11",
      "views": "29",
      "uploaded_time": "Aug 25,19"
    },
    {
      "chapter_name": "Vol.2 Chapter 10 : The Pulse Of Battle",
      "chapter_url": "https://chapmanganelo.com/manga-sg106726/chapter-10",
      "views": "31",
      "uploaded_time": "Aug 25,19"
    },
    {
      "chapter_name": "Vol.2 Chapter 9 : Level 4",
      "chapter_url": "https://chapmanganelo.com/manga-sg106726/chapter-9",
      "views": "30",
      "uploaded_time": "Aug 25,19"
    },
    {
      "chapter_name": "Vol.2 Chapter 8 : One Step Towards The Truth",
      "chapter_url": "https://chapmanganelo.com/manga-sg106726/chapter-8",
      "views": "30",
      "uploaded_time": "Aug 25,19"
    },
    {
      "chapter_name": "Vol.2 Chapter 7 : And Then, Alone...",
      "chapter_url": "https://chapmanganelo.com/manga-sg106726/chapter-7",
      "views": "32",
      "uploaded_time": "Aug 25,19"
    },
    {
      "chapter_name": "Vol.2 Chapter 6 : Into The Black Abyss",
      "chapter_url": "https://chapmanganelo.com/manga-sg106726/chapter-6",
      "views": "32",
      "uploaded_time": "Aug 25,19"
    },
    {
      "chapter_name": "Vol.1 Chapter 5 : The Girl Of Thorns",
      "chapter_url": "https://chapmanganelo.com/manga-sg106726/chapter-5",
      "views": "35",
      "uploaded_time": "Aug 25,19"
    },
    {
      "chapter_name": "Vol.1 Chapter 4 : The Face Of The Future",
      "chapter_url": "https://chapmanganelo.com/manga-sg106726/chapter-4",
      "views": "33",
      "uploaded_time": "Aug 25,19"
    },
    {
      "chapter_name": "Vol.1 Chapter 3 : That Day",
      "chapter_url": "https://chapmanganelo.com/manga-sg106726/chapter-3",
      "views": "35",
      "uploaded_time": "Aug 25,19"
    },
    {
      "chapter_name": "Vol.1 Chapter 2 : Those Trapped By Thorns",
      "chapter_url": "https://chapmanganelo.com/manga-sg106726/chapter-2",
      "views": "39",
      "uploaded_time": "Aug 25,19"
    },
    {
      "chapter_name": "Vol.1 Chapter 1 : The Chosen Ones",
      "chapter_url": "https://chapmanganelo.com/manga-sg106726/chapter-1",
      "views": "58",
      "uploaded_time": "Aug 25,19"
    }
  ]
}