{
  "title": "A Capricious Cat And A Shy Lion",
  "img": "https://avt.mkklcdnv6temp.com/fld/87/j/18-1734102390-nw.webp",
  "alternative_title": "Kimagure Neko to Kiyowa na Lion",
  "authors": [],
  "status": "Kimagure Neko to Kiyowa na Lion",
  "genres": [
    "Naoto Enu",
    "Smut",
    "Yaoi"
  ],
  "updated_time": "Dec 19,2024 - 02:02 AM",
  "description": "Description :\r\n        Yasukazu is a scary-faced businessman who adores cats. One day? while in the middle of brooding over how bad he is with the female customers in cat cafes? he happens to discover one with a majority of male customers. While he unwinds with cute cats he starts falling in love with the devilishly se** Jun who works there! Can love prevail between the scary-looking cat lover and the quirky cafe manager...? Immerse yourself in this steamy yaoi comedy and let the kitties and men wash the stress away!",
  "chapters": [
    {
      "chapter_name": "Chapter 0",
      "chapter_url": "https://chapmanganelo.com/manga-cm143480/chapter-0",
      "views": "3",
      "uploaded_time": "Dec 19,24"
    }
  ]
}