{
  "title": "Fujishiro-San Kei. (Ii)",
  "img": "https://avt.mkklcdnv6temp.com/fld/16/p/5-1732766570-nw.webp",
  "alternative_title": "\u00e8\u2014\u00a4\u00e4\u00bb\u00a3\u00e3\u0081\u2022\u00e3\u201a\u201c\u00e7\u00b3\u00bb\u00e3\u20ac\u201a (II) ; Fujishiro-san Kei (II)",
  "authors": [],
  "status": "\u00e8\u2014\u00a4\u00e4\u00bb\u00a3\u00e3\u0081\u2022\u00e3\u201a\u201c\u00e7\u00b3\u00bb\u00e3\u20ac\u201a (II) ; Fujishiro-san Kei (II)",
  "genres": [
    "Yuki Nojin",
    "Shoujo"
  ],
  "updated_time": "Jan 20,2016 - 12:22 PM",
  "description": "Description :\r\n        Note: This work is not be be confused with the oneshot collection manga under the same name by the same artist.",
  "chapters": [
    {
      "chapter_name": "Chapter 1",
      "chapter_url": "https://chapmanganelo.com/manga-my101218/chapter-1",
      "views": "15",
      "uploaded_time": "Aug 25,19"
    }
  ]
}