{
  "title": "Mirage",
  "img": "https://avt.mkklcdnv6temp.com/fld/81/i/16-1733319191-nw.webp",
  "alternative_title": "\ubbf8\ub77c\uc8fc",
  "authors": [],
  "status": "\ubbf8\ub77c\uc8fc",
  "genres": [
    "Park Dae Hyuk",
    "Action",
    "Mystery"
  ],
  "updated_time": "Feb 19,2024 - 23:24 PM",
  "description": "Description :\r\n        Han Nari is a high school girl, who knows every strategy for all the games in the world and is practically a pro gamer in theory.Her brother, Han Haeun, might seem like an ordinary student, but in the gaming world, he's unleashed without limits.These siblings combine their strengths to flawlessly conquer 'Mirage', the virtual reality game.But there's something unusual about these games. They experience pain in the virtual world just as they would in reality. And in a horror game, no less?!",
  "chapters": [
    {
      "chapter_name": "Chapter 6",
      "chapter_url": "https://chapmanganelo.com/manga-xb137969/chapter-6",
      "views": "11",
      "uploaded_time": "Feb 19,24"
    },
    {
      "chapter_name": "Chapter 5",
      "chapter_url": "https://chapmanganelo.com/manga-xb137969/chapter-5",
      "views": "8",
      "uploaded_time": "Feb 19,24"
    },
    {
      "chapter_name": "Chapter 4",
      "chapter_url": "https://chapmanganelo.com/manga-xb137969/chapter-4",
      "views": "10",
      "uploaded_time": "Feb 11,24"
    },
    {
      "chapter_name": "Chapter 3",
      "chapter_url": "https://chapmanganelo.com/manga-xb137969/chapter-3",
      "views": "8",
      "uploaded_time": "Feb 10,24"
    },
    {
      "chapter_name": "Chapter 2",
      "chapter_url": "https://chapmanganelo.com/manga-xb137969/chapter-2",
      "views": "11",
      "uploaded_time": "Feb 10,24"
    },
    {
      "chapter_name": "Chapter 1",
      "chapter_url": "https://chapmanganelo.com/manga-xb137969/chapter-1",
      "views": "15",
      "uploaded_time": "Feb 10,24"
    }
  ]
}