{
  "title": "Kimi Ga Dotei Dakara",
  "img": "https://avt.mkklcdnv6temp.com/fld/94/c/17-1733326850-nw.webp",
  "alternative_title": "Because You're Inexperienced ; Kimi ga Doutei dakara ; \u304d\u307f\u304c\u7ae5\u8c9e\u3060\u304b\u3089",
  "authors": [],
  "status": "Because You're Inexperienced ; Kimi ga Doutei dakara ; \u304d\u307f\u304c\u7ae5\u8c9e\u3060\u304b\u3089",
  "genres": [
    "Tamuko Kuwata",
    "Smut",
    "Yaoi"
  ],
  "updated_time": "Dec 08,2024 - 05:32 AM",
  "description": "Description :\r\n        Shiina, who prefers the company of the innocent and inexperienced, has a policy to just hook up, leave, and never get serious with anyone. That is, until he meets Sota, a hot, inexperienced college student. Shiina happily takes Sota to a hotel for the night, but isn't able to go all the way with Sota after seeing the big gun he's packing. However, Shiina can't let someone so good (a hung inexperienced hottie) get away! Shiina promises Sota he'll be ready the next time, but finds himself drawn more and more to his sweetness!+",
  "chapters": [
    {
      "chapter_name": "Chapter 9",
      "chapter_url": "https://chapmanganelo.com/manga-au140914/chapter-9",
      "views": "5",
      "uploaded_time": "Dec 08,24"
    },
    {
      "chapter_name": "Chapter 8",
      "chapter_url": "https://chapmanganelo.com/manga-au140914/chapter-8",
      "views": "6",
      "uploaded_time": "Nov 07,24"
    },
    {
      "chapter_name": "Chapter 7",
      "chapter_url": "https://chapmanganelo.com/manga-au140914/chapter-7",
      "views": "8",
      "uploaded_time": "Oct 23,24"
    },
    {
      "chapter_name": "Chapter 6",
      "chapter_url": "https://chapmanganelo.com/manga-au140914/chapter-6",
      "views": "10",
      "uploaded_time": "Sep 26,24"
    },
    {
      "chapter_name": "Chapter 5",
      "chapter_url": "https://chapmanganelo.com/manga-au140914/chapter-5",
      "views": "11",
      "uploaded_time": "Aug 30,24"
    },
    {
      "chapter_name": "Chapter 4",
      "chapter_url": "https://chapmanganelo.com/manga-au140914/chapter-4",
      "views": "10",
      "uploaded_time": "Aug 30,24"
    },
    {
      "chapter_name": "Chapter 3",
      "chapter_url": "https://chapmanganelo.com/manga-au140914/chapter-3",
      "views": "10",
      "uploaded_time": "Aug 30,24"
    },
    {
      "chapter_name": "Chapter 2",
      "chapter_url": "https://chapmanganelo.com/manga-au140914/chapter-2",
      "views": "12",
      "uploaded_time": "Aug 30,24"
    },
    {
      "chapter_name": "Chapter 1",
      "chapter_url": "https://chapmanganelo.com/manga-au140914/chapter-1",
      "views": "14",
      "uploaded_time": "Aug 30,24"
    }
  ]
}